{
  "lastUpdated" : "2025-12-23",
  "stockName" : "대신증권",
  "prices" : [ {
    "volume" : 56828,
    "marketCap" : 835730164000,
    "lowPrice" : 16340,
    "highPrice" : 16490,
    "openPrice" : 16390,
    "tradeDate" : "2024-12-23",
    "closePrice" : 16460
  }, {
    "volume" : 69731,
    "marketCap" : 844361642000,
    "lowPrice" : 16380,
    "highPrice" : 16660,
    "openPrice" : 16460,
    "tradeDate" : "2024-12-24",
    "closePrice" : 16630
  }, {
    "volume" : 195321,
    "marketCap" : 844869376000,
    "lowPrice" : 16450,
    "highPrice" : 16850,
    "openPrice" : 16800,
    "tradeDate" : "2024-12-26",
    "closePrice" : 16640
  }, {
    "volume" : 80657,
    "marketCap" : 830145090000,
    "lowPrice" : 16110,
    "highPrice" : 16450,
    "openPrice" : 16450,
    "tradeDate" : "2024-12-27",
    "closePrice" : 16350
  }, {
    "volume" : 63004,
    "marketCap" : 815928538000,
    "lowPrice" : 16010,
    "highPrice" : 16340,
    "openPrice" : 16210,
    "tradeDate" : "2024-12-30",
    "closePrice" : 16070
  }, {
    "volume" : 77996,
    "marketCap" : 813389868000,
    "lowPrice" : 15910,
    "highPrice" : 16080,
    "openPrice" : 15950,
    "tradeDate" : "2025-01-02",
    "closePrice" : 16020
  }, {
    "volume" : 134300,
    "marketCap" : 805266124000,
    "lowPrice" : 15860,
    "highPrice" : 16220,
    "openPrice" : 16030,
    "tradeDate" : "2025-01-03",
    "closePrice" : 15860
  }, {
    "volume" : 68706,
    "marketCap" : 808820262000,
    "lowPrice" : 15800,
    "highPrice" : 15990,
    "openPrice" : 15870,
    "tradeDate" : "2025-01-06",
    "closePrice" : 15930
  }, {
    "volume" : 88775,
    "marketCap" : 807804794000,
    "lowPrice" : 15860,
    "highPrice" : 16070,
    "openPrice" : 15930,
    "tradeDate" : "2025-01-07",
    "closePrice" : 15910
  }, {
    "volume" : 112220,
    "marketCap" : 802727454000,
    "lowPrice" : 15800,
    "highPrice" : 15970,
    "openPrice" : 15860,
    "tradeDate" : "2025-01-08",
    "closePrice" : 15810
  }, {
    "volume" : 72211,
    "marketCap" : 804250656000,
    "lowPrice" : 15780,
    "highPrice" : 15930,
    "openPrice" : 15810,
    "tradeDate" : "2025-01-09",
    "closePrice" : 15840
  }, {
    "volume" : 39294,
    "marketCap" : 807297060000,
    "lowPrice" : 15760,
    "highPrice" : 15900,
    "openPrice" : 15840,
    "tradeDate" : "2025-01-10",
    "closePrice" : 15900
  }, {
    "volume" : 122835,
    "marketCap" : 807804794000,
    "lowPrice" : 15840,
    "highPrice" : 16140,
    "openPrice" : 15900,
    "tradeDate" : "2025-01-13",
    "closePrice" : 15910
  }, {
    "volume" : 70056,
    "marketCap" : 810851198000,
    "lowPrice" : 15870,
    "highPrice" : 16050,
    "openPrice" : 15910,
    "tradeDate" : "2025-01-14",
    "closePrice" : 15970
  }, {
    "volume" : 101133,
    "marketCap" : 816944006000,
    "lowPrice" : 15970,
    "highPrice" : 16170,
    "openPrice" : 15990,
    "tradeDate" : "2025-01-15",
    "closePrice" : 16090
  }, {
    "volume" : 41646,
    "marketCap" : 817959474000,
    "lowPrice" : 16110,
    "highPrice" : 16220,
    "openPrice" : 16220,
    "tradeDate" : "2025-01-16",
    "closePrice" : 16110
  }, {
    "volume" : 44742,
    "marketCap" : 820498144000,
    "lowPrice" : 16040,
    "highPrice" : 16260,
    "openPrice" : 16040,
    "tradeDate" : "2025-01-17",
    "closePrice" : 16160
  }, {
    "volume" : 30970,
    "marketCap" : 825575484000,
    "lowPrice" : 16180,
    "highPrice" : 16270,
    "openPrice" : 16220,
    "tradeDate" : "2025-01-20",
    "closePrice" : 16260
  }, {
    "volume" : 27661,
    "marketCap" : 826083218000,
    "lowPrice" : 16220,
    "highPrice" : 16340,
    "openPrice" : 16260,
    "tradeDate" : "2025-01-21",
    "closePrice" : 16270
  }, {
    "volume" : 45615,
    "marketCap" : 826590952000,
    "lowPrice" : 16150,
    "highPrice" : 16320,
    "openPrice" : 16240,
    "tradeDate" : "2025-01-22",
    "closePrice" : 16280
  }, {
    "volume" : 53001,
    "marketCap" : 827098686000,
    "lowPrice" : 16230,
    "highPrice" : 16350,
    "openPrice" : 16280,
    "tradeDate" : "2025-01-23",
    "closePrice" : 16290
  }, {
    "volume" : 39718,
    "marketCap" : 831668292000,
    "lowPrice" : 16280,
    "highPrice" : 16400,
    "openPrice" : 16360,
    "tradeDate" : "2025-01-24",
    "closePrice" : 16380
  }, {
    "volume" : 89353,
    "marketCap" : 842838440000,
    "lowPrice" : 16360,
    "highPrice" : 16710,
    "openPrice" : 16380,
    "tradeDate" : "2025-01-31",
    "closePrice" : 16600
  }, {
    "volume" : 87076,
    "marketCap" : 840807504000,
    "lowPrice" : 16320,
    "highPrice" : 16600,
    "openPrice" : 16550,
    "tradeDate" : "2025-02-03",
    "closePrice" : 16560
  }, {
    "volume" : 46671,
    "marketCap" : 847408046000,
    "lowPrice" : 16580,
    "highPrice" : 16700,
    "openPrice" : 16690,
    "tradeDate" : "2025-02-04",
    "closePrice" : 16690
  }, {
    "volume" : 72769,
    "marketCap" : 850962184000,
    "lowPrice" : 16580,
    "highPrice" : 16760,
    "openPrice" : 16720,
    "tradeDate" : "2025-02-05",
    "closePrice" : 16760
  }, {
    "volume" : 78813,
    "marketCap" : 852993120000,
    "lowPrice" : 16740,
    "highPrice" : 17040,
    "openPrice" : 16770,
    "tradeDate" : "2025-02-06",
    "closePrice" : 16800
  }, {
    "volume" : 64961,
    "marketCap" : 851469918000,
    "lowPrice" : 16600,
    "highPrice" : 16860,
    "openPrice" : 16850,
    "tradeDate" : "2025-02-07",
    "closePrice" : 16770
  }, {
    "volume" : 57534,
    "marketCap" : 845884844000,
    "lowPrice" : 16600,
    "highPrice" : 16760,
    "openPrice" : 16730,
    "tradeDate" : "2025-02-10",
    "closePrice" : 16660
  }, {
    "volume" : 85745,
    "marketCap" : 841822972000,
    "lowPrice" : 16500,
    "highPrice" : 16730,
    "openPrice" : 16660,
    "tradeDate" : "2025-02-11",
    "closePrice" : 16580
  }, {
    "volume" : 52185,
    "marketCap" : 847915780000,
    "lowPrice" : 16550,
    "highPrice" : 16700,
    "openPrice" : 16550,
    "tradeDate" : "2025-02-12",
    "closePrice" : 16700
  }, {
    "volume" : 46142,
    "marketCap" : 846900312000,
    "lowPrice" : 16560,
    "highPrice" : 16730,
    "openPrice" : 16700,
    "tradeDate" : "2025-02-13",
    "closePrice" : 16680
  }, {
    "volume" : 37646,
    "marketCap" : 854516322000,
    "lowPrice" : 16720,
    "highPrice" : 16860,
    "openPrice" : 16740,
    "tradeDate" : "2025-02-14",
    "closePrice" : 16830
  }, {
    "volume" : 66438,
    "marketCap" : 862640066000,
    "lowPrice" : 16750,
    "highPrice" : 17010,
    "openPrice" : 16750,
    "tradeDate" : "2025-02-17",
    "closePrice" : 16990
  }, {
    "volume" : 56262,
    "marketCap" : 865178736000,
    "lowPrice" : 16950,
    "highPrice" : 17080,
    "openPrice" : 16960,
    "tradeDate" : "2025-02-18",
    "closePrice" : 17040
  }, {
    "volume" : 83444,
    "marketCap" : 868732874000,
    "lowPrice" : 16980,
    "highPrice" : 17200,
    "openPrice" : 16980,
    "tradeDate" : "2025-02-19",
    "closePrice" : 17110
  }, {
    "volume" : 59752,
    "marketCap" : 874317948000,
    "lowPrice" : 17110,
    "highPrice" : 17250,
    "openPrice" : 17150,
    "tradeDate" : "2025-02-20",
    "closePrice" : 17220
  }, {
    "volume" : 52077,
    "marketCap" : 876348884000,
    "lowPrice" : 17160,
    "highPrice" : 17290,
    "openPrice" : 17220,
    "tradeDate" : "2025-02-21",
    "closePrice" : 17260
  }, {
    "volume" : 42559,
    "marketCap" : 876348884000,
    "lowPrice" : 17150,
    "highPrice" : 17330,
    "openPrice" : 17250,
    "tradeDate" : "2025-02-24",
    "closePrice" : 17260
  }, {
    "volume" : 47837,
    "marketCap" : 872794746000,
    "lowPrice" : 17140,
    "highPrice" : 17290,
    "openPrice" : 17200,
    "tradeDate" : "2025-02-25",
    "closePrice" : 17190
  }, {
    "volume" : 71741,
    "marketCap" : 869748342000,
    "lowPrice" : 17000,
    "highPrice" : 17200,
    "openPrice" : 17140,
    "tradeDate" : "2025-02-26",
    "closePrice" : 17130
  }, {
    "volume" : 41449,
    "marketCap" : 870763810000,
    "lowPrice" : 16990,
    "highPrice" : 17150,
    "openPrice" : 17130,
    "tradeDate" : "2025-02-27",
    "closePrice" : 17150
  }, {
    "volume" : 44710,
    "marketCap" : 858070460000,
    "lowPrice" : 16900,
    "highPrice" : 17130,
    "openPrice" : 17130,
    "tradeDate" : "2025-02-28",
    "closePrice" : 16900
  }, {
    "volume" : 59393,
    "marketCap" : 848423514000,
    "lowPrice" : 16670,
    "highPrice" : 16880,
    "openPrice" : 16810,
    "tradeDate" : "2025-03-04",
    "closePrice" : 16710
  }, {
    "volume" : 52773,
    "marketCap" : 846900312000,
    "lowPrice" : 16570,
    "highPrice" : 16870,
    "openPrice" : 16710,
    "tradeDate" : "2025-03-05",
    "closePrice" : 16680
  }, {
    "volume" : 46818,
    "marketCap" : 861116864000,
    "lowPrice" : 16680,
    "highPrice" : 16960,
    "openPrice" : 16680,
    "tradeDate" : "2025-03-06",
    "closePrice" : 16960
  }, {
    "volume" : 65298,
    "marketCap" : 857562726000,
    "lowPrice" : 16820,
    "highPrice" : 17100,
    "openPrice" : 16930,
    "tradeDate" : "2025-03-07",
    "closePrice" : 16890
  }, {
    "volume" : 94979,
    "marketCap" : 868225140000,
    "lowPrice" : 16840,
    "highPrice" : 17260,
    "openPrice" : 17040,
    "tradeDate" : "2025-03-10",
    "closePrice" : 17100
  }, {
    "volume" : 68027,
    "marketCap" : 856547258000,
    "lowPrice" : 16840,
    "highPrice" : 17030,
    "openPrice" : 16950,
    "tradeDate" : "2025-03-11",
    "closePrice" : 16870
  }, {
    "volume" : 65645,
    "marketCap" : 858070460000,
    "lowPrice" : 16860,
    "highPrice" : 17040,
    "openPrice" : 16870,
    "tradeDate" : "2025-03-12",
    "closePrice" : 16900
  }, {
    "volume" : 86839,
    "marketCap" : 858578194000,
    "lowPrice" : 16820,
    "highPrice" : 17020,
    "openPrice" : 16900,
    "tradeDate" : "2025-03-13",
    "closePrice" : 16910
  }, {
    "volume" : 63545,
    "marketCap" : 860101396000,
    "lowPrice" : 16860,
    "highPrice" : 17020,
    "openPrice" : 16880,
    "tradeDate" : "2025-03-14",
    "closePrice" : 16940
  }, {
    "volume" : 176392,
    "marketCap" : 871779278000,
    "lowPrice" : 16790,
    "highPrice" : 17220,
    "openPrice" : 16940,
    "tradeDate" : "2025-03-17",
    "closePrice" : 17170
  }, {
    "volume" : 161050,
    "marketCap" : 878887554000,
    "lowPrice" : 17150,
    "highPrice" : 17330,
    "openPrice" : 17170,
    "tradeDate" : "2025-03-18",
    "closePrice" : 17310
  }, {
    "volume" : 136646,
    "marketCap" : 875841150000,
    "lowPrice" : 17240,
    "highPrice" : 17400,
    "openPrice" : 17310,
    "tradeDate" : "2025-03-19",
    "closePrice" : 17250
  }, {
    "volume" : 196857,
    "marketCap" : 871271544000,
    "lowPrice" : 17150,
    "highPrice" : 17300,
    "openPrice" : 17300,
    "tradeDate" : "2025-03-20",
    "closePrice" : 17160
  }, {
    "volume" : 227189,
    "marketCap" : 875841150000,
    "lowPrice" : 16910,
    "highPrice" : 17270,
    "openPrice" : 17160,
    "tradeDate" : "2025-03-21",
    "closePrice" : 17250
  }, {
    "volume" : 335105,
    "marketCap" : 876856618000,
    "lowPrice" : 17270,
    "highPrice" : 17410,
    "openPrice" : 17300,
    "tradeDate" : "2025-03-24",
    "closePrice" : 17270
  }, {
    "volume" : 420808,
    "marketCap" : 819990410000,
    "lowPrice" : 16110,
    "highPrice" : 16420,
    "openPrice" : 16300,
    "tradeDate" : "2025-03-25",
    "closePrice" : 16150
  }, {
    "volume" : 165659,
    "marketCap" : 828621888000,
    "lowPrice" : 16000,
    "highPrice" : 16330,
    "openPrice" : 16150,
    "tradeDate" : "2025-03-26",
    "closePrice" : 16320
  }, {
    "volume" : 98411,
    "marketCap" : 828621888000,
    "lowPrice" : 16170,
    "highPrice" : 16390,
    "openPrice" : 16310,
    "tradeDate" : "2025-03-27",
    "closePrice" : 16320
  }, {
    "volume" : 65124,
    "marketCap" : 830145090000,
    "lowPrice" : 16210,
    "highPrice" : 16360,
    "openPrice" : 16310,
    "tradeDate" : "2025-03-28",
    "closePrice" : 16350
  }, {
    "volume" : 73895,
    "marketCap" : 823544548000,
    "lowPrice" : 16160,
    "highPrice" : 16340,
    "openPrice" : 16340,
    "tradeDate" : "2025-03-31",
    "closePrice" : 16220
  }, {
    "volume" : 46454,
    "marketCap" : 826083218000,
    "lowPrice" : 16150,
    "highPrice" : 16360,
    "openPrice" : 16360,
    "tradeDate" : "2025-04-01",
    "closePrice" : 16270
  }, {
    "volume" : 34226,
    "marketCap" : 828114154000,
    "lowPrice" : 16200,
    "highPrice" : 16350,
    "openPrice" : 16350,
    "tradeDate" : "2025-04-02",
    "closePrice" : 16310
  }, {
    "volume" : 57164,
    "marketCap" : 825067750000,
    "lowPrice" : 16170,
    "highPrice" : 16350,
    "openPrice" : 16290,
    "tradeDate" : "2025-04-03",
    "closePrice" : 16250
  }, {
    "volume" : 37937,
    "marketCap" : 824052282000,
    "lowPrice" : 16140,
    "highPrice" : 16280,
    "openPrice" : 16180,
    "tradeDate" : "2025-04-04",
    "closePrice" : 16230
  }, {
    "volume" : 101343,
    "marketCap" : 803742922000,
    "lowPrice" : 15770,
    "highPrice" : 16130,
    "openPrice" : 16080,
    "tradeDate" : "2025-04-07",
    "closePrice" : 15830
  }, {
    "volume" : 51431,
    "marketCap" : 803235188000,
    "lowPrice" : 15820,
    "highPrice" : 16060,
    "openPrice" : 15860,
    "tradeDate" : "2025-04-08",
    "closePrice" : 15820
  }, {
    "volume" : 74461,
    "marketCap" : 795619178000,
    "lowPrice" : 15560,
    "highPrice" : 15980,
    "openPrice" : 15980,
    "tradeDate" : "2025-04-09",
    "closePrice" : 15670
  }, {
    "volume" : 47308,
    "marketCap" : 818467208000,
    "lowPrice" : 15820,
    "highPrice" : 16150,
    "openPrice" : 16140,
    "tradeDate" : "2025-04-10",
    "closePrice" : 16120
  }, {
    "volume" : 42652,
    "marketCap" : 822529080000,
    "lowPrice" : 15980,
    "highPrice" : 16200,
    "openPrice" : 16050,
    "tradeDate" : "2025-04-11",
    "closePrice" : 16200
  }, {
    "volume" : 101084,
    "marketCap" : 830652824000,
    "lowPrice" : 16140,
    "highPrice" : 16360,
    "openPrice" : 16180,
    "tradeDate" : "2025-04-14",
    "closePrice" : 16360
  }, {
    "volume" : 63905,
    "marketCap" : 843853908000,
    "lowPrice" : 16320,
    "highPrice" : 16620,
    "openPrice" : 16370,
    "tradeDate" : "2025-04-15",
    "closePrice" : 16620
  }, {
    "volume" : 105040,
    "marketCap" : 855531790000,
    "lowPrice" : 16520,
    "highPrice" : 16870,
    "openPrice" : 16620,
    "tradeDate" : "2025-04-16",
    "closePrice" : 16850
  }, {
    "volume" : 51552,
    "marketCap" : 852485386000,
    "lowPrice" : 16630,
    "highPrice" : 16840,
    "openPrice" : 16840,
    "tradeDate" : "2025-04-17",
    "closePrice" : 16790
  }, {
    "volume" : 58646,
    "marketCap" : 859593662000,
    "lowPrice" : 16780,
    "highPrice" : 16940,
    "openPrice" : 16800,
    "tradeDate" : "2025-04-18",
    "closePrice" : 16930
  }, {
    "volume" : 115060,
    "marketCap" : 875333416000,
    "lowPrice" : 16880,
    "highPrice" : 17240,
    "openPrice" : 16910,
    "tradeDate" : "2025-04-21",
    "closePrice" : 17240
  }, {
    "volume" : 171345,
    "marketCap" : 885488096000,
    "lowPrice" : 17120,
    "highPrice" : 17510,
    "openPrice" : 17120,
    "tradeDate" : "2025-04-22",
    "closePrice" : 17440
  }, {
    "volume" : 66343,
    "marketCap" : 882441692000,
    "lowPrice" : 17350,
    "highPrice" : 17500,
    "openPrice" : 17450,
    "tradeDate" : "2025-04-23",
    "closePrice" : 17380
  }, {
    "volume" : 41497,
    "marketCap" : 882949426000,
    "lowPrice" : 17320,
    "highPrice" : 17470,
    "openPrice" : 17360,
    "tradeDate" : "2025-04-24",
    "closePrice" : 17390
  }, {
    "volume" : 39738,
    "marketCap" : 879903022000,
    "lowPrice" : 17210,
    "highPrice" : 17490,
    "openPrice" : 17400,
    "tradeDate" : "2025-04-25",
    "closePrice" : 17330
  }, {
    "volume" : 36971,
    "marketCap" : 877872086000,
    "lowPrice" : 17230,
    "highPrice" : 17380,
    "openPrice" : 17290,
    "tradeDate" : "2025-04-28",
    "closePrice" : 17290
  }, {
    "volume" : 124377,
    "marketCap" : 891580904000,
    "lowPrice" : 17280,
    "highPrice" : 17570,
    "openPrice" : 17370,
    "tradeDate" : "2025-04-29",
    "closePrice" : 17560
  }, {
    "volume" : 184065,
    "marketCap" : 910367062000,
    "lowPrice" : 17530,
    "highPrice" : 18000,
    "openPrice" : 17600,
    "tradeDate" : "2025-04-30",
    "closePrice" : 17930
  }, {
    "volume" : 72982,
    "marketCap" : 909859328000,
    "lowPrice" : 17620,
    "highPrice" : 18040,
    "openPrice" : 18020,
    "tradeDate" : "2025-05-02",
    "closePrice" : 17920
  }, {
    "volume" : 128429,
    "marketCap" : 930168688000,
    "lowPrice" : 17920,
    "highPrice" : 18480,
    "openPrice" : 17920,
    "tradeDate" : "2025-05-07",
    "closePrice" : 18320
  }, {
    "volume" : 185091,
    "marketCap" : 961140462000,
    "lowPrice" : 18320,
    "highPrice" : 19000,
    "openPrice" : 18320,
    "tradeDate" : "2025-05-08",
    "closePrice" : 18930
  }, {
    "volume" : 87000,
    "marketCap" : 964694600000,
    "lowPrice" : 18930,
    "highPrice" : 19220,
    "openPrice" : 19210,
    "tradeDate" : "2025-05-09",
    "closePrice" : 19000
  }, {
    "volume" : 173385,
    "marketCap" : 985511694000,
    "lowPrice" : 18980,
    "highPrice" : 19620,
    "openPrice" : 19000,
    "tradeDate" : "2025-05-12",
    "closePrice" : 19410
  }, {
    "volume" : 210917,
    "marketCap" : 1009375192000,
    "lowPrice" : 19330,
    "highPrice" : 20000,
    "openPrice" : 19590,
    "tradeDate" : "2025-05-13",
    "closePrice" : 19880
  }, {
    "volume" : 157395,
    "marketCap" : 1008867458000,
    "lowPrice" : 19790,
    "highPrice" : 20150,
    "openPrice" : 20000,
    "tradeDate" : "2025-05-14",
    "closePrice" : 19870
  }, {
    "volume" : 153634,
    "marketCap" : 1009375192000,
    "lowPrice" : 19670,
    "highPrice" : 20100,
    "openPrice" : 19870,
    "tradeDate" : "2025-05-15",
    "closePrice" : 19880
  }, {
    "volume" : 183620,
    "marketCap" : 1013437064000,
    "lowPrice" : 19290,
    "highPrice" : 20000,
    "openPrice" : 20000,
    "tradeDate" : "2025-05-16",
    "closePrice" : 19960
  }, {
    "volume" : 107008,
    "marketCap" : 982973024000,
    "lowPrice" : 19250,
    "highPrice" : 20000,
    "openPrice" : 19750,
    "tradeDate" : "2025-05-19",
    "closePrice" : 19360
  }, {
    "volume" : 189634,
    "marketCap" : 1020545340000,
    "lowPrice" : 19620,
    "highPrice" : 20200,
    "openPrice" : 20100,
    "tradeDate" : "2025-05-20",
    "closePrice" : 20100
  }, {
    "volume" : 229519,
    "marketCap" : 1045932040000,
    "lowPrice" : 19920,
    "highPrice" : 20650,
    "openPrice" : 20100,
    "tradeDate" : "2025-05-21",
    "closePrice" : 20600
  }, {
    "volume" : 105040,
    "marketCap" : 1045932040000,
    "lowPrice" : 20200,
    "highPrice" : 20750,
    "openPrice" : 20550,
    "tradeDate" : "2025-05-22",
    "closePrice" : 20600
  }, {
    "volume" : 125637,
    "marketCap" : 1053548050000,
    "lowPrice" : 20350,
    "highPrice" : 21000,
    "openPrice" : 20650,
    "tradeDate" : "2025-05-23",
    "closePrice" : 20750
  }, {
    "volume" : 81002,
    "marketCap" : 1053548050000,
    "lowPrice" : 20550,
    "highPrice" : 20900,
    "openPrice" : 20800,
    "tradeDate" : "2025-05-26",
    "closePrice" : 20750
  }, {
    "volume" : 88799,
    "marketCap" : 1048470710000,
    "lowPrice" : 20350,
    "highPrice" : 20800,
    "openPrice" : 20750,
    "tradeDate" : "2025-05-27",
    "closePrice" : 20650
  }, {
    "volume" : 149019,
    "marketCap" : 1045932040000,
    "lowPrice" : 20500,
    "highPrice" : 20950,
    "openPrice" : 20700,
    "tradeDate" : "2025-05-28",
    "closePrice" : 20600
  }, {
    "volume" : 403303,
    "marketCap" : 1144940170000,
    "lowPrice" : 20800,
    "highPrice" : 22550,
    "openPrice" : 20800,
    "tradeDate" : "2025-05-29",
    "closePrice" : 22550
  }, {
    "volume" : 287353,
    "marketCap" : 1165249530000,
    "lowPrice" : 22250,
    "highPrice" : 23600,
    "openPrice" : 23450,
    "tradeDate" : "2025-05-30",
    "closePrice" : 22950
  }, {
    "volume" : 264423,
    "marketCap" : 1172865540000,
    "lowPrice" : 22500,
    "highPrice" : 24150,
    "openPrice" : 23300,
    "tradeDate" : "2025-06-02",
    "closePrice" : 23100
  }, {
    "volume" : 374311,
    "marketCap" : 1218561600000,
    "lowPrice" : 23400,
    "highPrice" : 24500,
    "openPrice" : 23550,
    "tradeDate" : "2025-06-04",
    "closePrice" : 24000
  }, {
    "volume" : 244920,
    "marketCap" : 1231254950000,
    "lowPrice" : 23950,
    "highPrice" : 25000,
    "openPrice" : 24800,
    "tradeDate" : "2025-06-05",
    "closePrice" : 24250
  }, {
    "volume" : 397076,
    "marketCap" : 1289644360000,
    "lowPrice" : 24950,
    "highPrice" : 26600,
    "openPrice" : 24950,
    "tradeDate" : "2025-06-09",
    "closePrice" : 25400
  }, {
    "volume" : 275096,
    "marketCap" : 1269335000000,
    "lowPrice" : 24650,
    "highPrice" : 25850,
    "openPrice" : 25800,
    "tradeDate" : "2025-06-10",
    "closePrice" : 25000
  }, {
    "volume" : 263927,
    "marketCap" : 1259180320000,
    "lowPrice" : 24175,
    "highPrice" : 24950,
    "openPrice" : 24950,
    "tradeDate" : "2025-06-11",
    "closePrice" : 24800
  }, {
    "volume" : 269775,
    "marketCap" : 1238870960000,
    "lowPrice" : 24250,
    "highPrice" : 25100,
    "openPrice" : 25100,
    "tradeDate" : "2025-06-12",
    "closePrice" : 24400
  }, {
    "volume" : 371581,
    "marketCap" : 1251564310000,
    "lowPrice" : 24175,
    "highPrice" : 25450,
    "openPrice" : 24950,
    "tradeDate" : "2025-06-13",
    "closePrice" : 24650
  }, {
    "volume" : 343391,
    "marketCap" : 1259180320000,
    "lowPrice" : 24350,
    "highPrice" : 25150,
    "openPrice" : 24350,
    "tradeDate" : "2025-06-16",
    "closePrice" : 24800
  }, {
    "volume" : 618607,
    "marketCap" : 1241409630000,
    "lowPrice" : 23900,
    "highPrice" : 25650,
    "openPrice" : 25350,
    "tradeDate" : "2025-06-17",
    "closePrice" : 24450
  }, {
    "volume" : 164368,
    "marketCap" : 1243948300000,
    "lowPrice" : 24150,
    "highPrice" : 24750,
    "openPrice" : 24250,
    "tradeDate" : "2025-06-18",
    "closePrice" : 24500
  }, {
    "volume" : 164980,
    "marketCap" : 1226177610000,
    "lowPrice" : 23750,
    "highPrice" : 24800,
    "openPrice" : 24650,
    "tradeDate" : "2025-06-19",
    "closePrice" : 24150
  }, {
    "volume" : 163446,
    "marketCap" : 1218561600000,
    "lowPrice" : 23750,
    "highPrice" : 24250,
    "openPrice" : 24250,
    "tradeDate" : "2025-06-20",
    "closePrice" : 24000
  }, {
    "volume" : 276580,
    "marketCap" : 1246486970000,
    "lowPrice" : 23500,
    "highPrice" : 24800,
    "openPrice" : 23500,
    "tradeDate" : "2025-06-23",
    "closePrice" : 24550
  }, {
    "volume" : 310518,
    "marketCap" : 1279489680000,
    "lowPrice" : 24700,
    "highPrice" : 25450,
    "openPrice" : 25100,
    "tradeDate" : "2025-06-24",
    "closePrice" : 25200
  }, {
    "volume" : 208717,
    "marketCap" : 1284567020000,
    "lowPrice" : 24850,
    "highPrice" : 25600,
    "openPrice" : 25500,
    "tradeDate" : "2025-06-25",
    "closePrice" : 25300
  }, {
    "volume" : 230574,
    "marketCap" : 1243948300000,
    "lowPrice" : 24050,
    "highPrice" : 25100,
    "openPrice" : 25100,
    "tradeDate" : "2025-06-26",
    "closePrice" : 24500
  }, {
    "volume" : 218630,
    "marketCap" : 1238870960000,
    "lowPrice" : 24150,
    "highPrice" : 24750,
    "openPrice" : 24500,
    "tradeDate" : "2025-06-27",
    "closePrice" : 24400
  }, {
    "volume" : 203564,
    "marketCap" : 1238870960000,
    "lowPrice" : 24100,
    "highPrice" : 24600,
    "openPrice" : 24600,
    "tradeDate" : "2025-06-30",
    "closePrice" : 24400
  }, {
    "volume" : 297374,
    "marketCap" : 1276951010000,
    "lowPrice" : 24550,
    "highPrice" : 25600,
    "openPrice" : 24650,
    "tradeDate" : "2025-07-01",
    "closePrice" : 25150
  }, {
    "volume" : 131111,
    "marketCap" : 1261718990000,
    "lowPrice" : 24300,
    "highPrice" : 25200,
    "openPrice" : 25200,
    "tradeDate" : "2025-07-02",
    "closePrice" : 24850
  }, {
    "volume" : 203613,
    "marketCap" : 1297260370000,
    "lowPrice" : 24850,
    "highPrice" : 25550,
    "openPrice" : 25250,
    "tradeDate" : "2025-07-03",
    "closePrice" : 25550
  }, {
    "volume" : 325229,
    "marketCap" : 1216022930000,
    "lowPrice" : 23900,
    "highPrice" : 25750,
    "openPrice" : 25550,
    "tradeDate" : "2025-07-04",
    "closePrice" : 23950
  }, {
    "volume" : 132706,
    "marketCap" : 1246486970000,
    "lowPrice" : 23500,
    "highPrice" : 24700,
    "openPrice" : 23850,
    "tradeDate" : "2025-07-07",
    "closePrice" : 24550
  }, {
    "volume" : 599288,
    "marketCap" : 1381036480000,
    "lowPrice" : 24350,
    "highPrice" : 27300,
    "openPrice" : 24550,
    "tradeDate" : "2025-07-08",
    "closePrice" : 27200
  }, {
    "volume" : 2316915,
    "marketCap" : 1533356680000,
    "lowPrice" : 27600,
    "highPrice" : 31550,
    "openPrice" : 29050,
    "tradeDate" : "2025-07-09",
    "closePrice" : 30200
  }, {
    "volume" : 693327,
    "marketCap" : 1520663330000,
    "lowPrice" : 29350,
    "highPrice" : 30950,
    "openPrice" : 29950,
    "tradeDate" : "2025-07-10",
    "closePrice" : 29950
  }, {
    "volume" : 817219,
    "marketCap" : 1586668750000,
    "lowPrice" : 29900,
    "highPrice" : 31500,
    "openPrice" : 30200,
    "tradeDate" : "2025-07-11",
    "closePrice" : 31250
  }, {
    "volume" : 522577,
    "marketCap" : 1606978110000,
    "lowPrice" : 30200,
    "highPrice" : 31950,
    "openPrice" : 31000,
    "tradeDate" : "2025-07-14",
    "closePrice" : 31650
  }, {
    "volume" : 431742,
    "marketCap" : 1584130080000,
    "lowPrice" : 30650,
    "highPrice" : 31850,
    "openPrice" : 31700,
    "tradeDate" : "2025-07-15",
    "closePrice" : 31200
  }, {
    "volume" : 469978,
    "marketCap" : 1513047320000,
    "lowPrice" : 29600,
    "highPrice" : 30500,
    "openPrice" : 30350,
    "tradeDate" : "2025-07-16",
    "closePrice" : 29800
  }, {
    "volume" : 303069,
    "marketCap" : 1497815300000,
    "lowPrice" : 28550,
    "highPrice" : 30050,
    "openPrice" : 30000,
    "tradeDate" : "2025-07-17",
    "closePrice" : 29500
  }, {
    "volume" : 339801,
    "marketCap" : 1444503230000,
    "lowPrice" : 28200,
    "highPrice" : 29500,
    "openPrice" : 29500,
    "tradeDate" : "2025-07-18",
    "closePrice" : 28450
  }, {
    "volume" : 223312,
    "marketCap" : 1429271210000,
    "lowPrice" : 27750,
    "highPrice" : 28450,
    "openPrice" : 28000,
    "tradeDate" : "2025-07-21",
    "closePrice" : 28150
  }, {
    "volume" : 388723,
    "marketCap" : 1447041900000,
    "lowPrice" : 27950,
    "highPrice" : 29300,
    "openPrice" : 29000,
    "tradeDate" : "2025-07-22",
    "closePrice" : 28500
  }, {
    "volume" : 272424,
    "marketCap" : 1398807170000,
    "lowPrice" : 27300,
    "highPrice" : 28450,
    "openPrice" : 28250,
    "tradeDate" : "2025-07-23",
    "closePrice" : 27550
  }, {
    "volume" : 224755,
    "marketCap" : 1383575150000,
    "lowPrice" : 27100,
    "highPrice" : 28300,
    "openPrice" : 27900,
    "tradeDate" : "2025-07-24",
    "closePrice" : 27250
  }, {
    "volume" : 154925,
    "marketCap" : 1378497810000,
    "lowPrice" : 27050,
    "highPrice" : 27950,
    "openPrice" : 27150,
    "tradeDate" : "2025-07-25",
    "closePrice" : 27150
  }, {
    "volume" : 393041,
    "marketCap" : 1297260370000,
    "lowPrice" : 25350,
    "highPrice" : 27150,
    "openPrice" : 27150,
    "tradeDate" : "2025-07-28",
    "closePrice" : 25550
  }, {
    "volume" : 152461,
    "marketCap" : 1299799040000,
    "lowPrice" : 25250,
    "highPrice" : 25800,
    "openPrice" : 25300,
    "tradeDate" : "2025-07-29",
    "closePrice" : 25600
  }, {
    "volume" : 133411,
    "marketCap" : 1292183030000,
    "lowPrice" : 25300,
    "highPrice" : 26150,
    "openPrice" : 26050,
    "tradeDate" : "2025-07-30",
    "closePrice" : 25450
  }, {
    "volume" : 284684,
    "marketCap" : 1297260370000,
    "lowPrice" : 25350,
    "highPrice" : 26000,
    "openPrice" : 25700,
    "tradeDate" : "2025-07-31",
    "closePrice" : 25550
  }, {
    "volume" : 403715,
    "marketCap" : 1200790910000,
    "lowPrice" : 23450,
    "highPrice" : 25350,
    "openPrice" : 25350,
    "tradeDate" : "2025-08-01",
    "closePrice" : 23650
  }, {
    "volume" : 134348,
    "marketCap" : 1223638940000,
    "lowPrice" : 23600,
    "highPrice" : 24100,
    "openPrice" : 23800,
    "tradeDate" : "2025-08-04",
    "closePrice" : 24100
  }, {
    "volume" : 196999,
    "marketCap" : 1251564310000,
    "lowPrice" : 24300,
    "highPrice" : 24800,
    "openPrice" : 24400,
    "tradeDate" : "2025-08-05",
    "closePrice" : 24650
  }, {
    "volume" : 84920,
    "marketCap" : 1261718990000,
    "lowPrice" : 24425,
    "highPrice" : 24900,
    "openPrice" : 24650,
    "tradeDate" : "2025-08-06",
    "closePrice" : 24850
  }, {
    "volume" : 116010,
    "marketCap" : 1274412340000,
    "lowPrice" : 24750,
    "highPrice" : 25400,
    "openPrice" : 25400,
    "tradeDate" : "2025-08-07",
    "closePrice" : 25100
  }, {
    "volume" : 67186,
    "marketCap" : 1279489680000,
    "lowPrice" : 24850,
    "highPrice" : 25250,
    "openPrice" : 25150,
    "tradeDate" : "2025-08-08",
    "closePrice" : 25200
  }, {
    "volume" : 283659,
    "marketCap" : 1264257660000,
    "lowPrice" : 24300,
    "highPrice" : 25950,
    "openPrice" : 25900,
    "tradeDate" : "2025-08-11",
    "closePrice" : 24900
  }, {
    "volume" : 394805,
    "marketCap" : 1294721700000,
    "lowPrice" : 24750,
    "highPrice" : 26550,
    "openPrice" : 24800,
    "tradeDate" : "2025-08-12",
    "closePrice" : 25500
  }, {
    "volume" : 126337,
    "marketCap" : 1294721700000,
    "lowPrice" : 25250,
    "highPrice" : 26150,
    "openPrice" : 26100,
    "tradeDate" : "2025-08-13",
    "closePrice" : 25500
  }, {
    "volume" : 69267,
    "marketCap" : 1279489680000,
    "lowPrice" : 25100,
    "highPrice" : 25700,
    "openPrice" : 25600,
    "tradeDate" : "2025-08-14",
    "closePrice" : 25200
  }, {
    "volume" : 78472,
    "marketCap" : 1256641650000,
    "lowPrice" : 24650,
    "highPrice" : 25100,
    "openPrice" : 25000,
    "tradeDate" : "2025-08-18",
    "closePrice" : 24750
  }, {
    "volume" : 79837,
    "marketCap" : 1254102980000,
    "lowPrice" : 24400,
    "highPrice" : 25000,
    "openPrice" : 24750,
    "tradeDate" : "2025-08-19",
    "closePrice" : 24700
  }, {
    "volume" : 131734,
    "marketCap" : 1249025640000,
    "lowPrice" : 23750,
    "highPrice" : 24800,
    "openPrice" : 24100,
    "tradeDate" : "2025-08-20",
    "closePrice" : 24600
  }, {
    "volume" : 85710,
    "marketCap" : 1259180320000,
    "lowPrice" : 24600,
    "highPrice" : 25050,
    "openPrice" : 24650,
    "tradeDate" : "2025-08-21",
    "closePrice" : 24800
  }, {
    "volume" : 67574,
    "marketCap" : 1256641650000,
    "lowPrice" : 24650,
    "highPrice" : 25150,
    "openPrice" : 24650,
    "tradeDate" : "2025-08-22",
    "closePrice" : 24750
  }, {
    "volume" : 165628,
    "marketCap" : 1315031060000,
    "lowPrice" : 25100,
    "highPrice" : 26000,
    "openPrice" : 25100,
    "tradeDate" : "2025-08-25",
    "closePrice" : 25900
  }, {
    "volume" : 97867,
    "marketCap" : 1299799040000,
    "lowPrice" : 25450,
    "highPrice" : 25850,
    "openPrice" : 25800,
    "tradeDate" : "2025-08-26",
    "closePrice" : 25600
  }, {
    "volume" : 55877,
    "marketCap" : 1307415050000,
    "lowPrice" : 25450,
    "highPrice" : 26100,
    "openPrice" : 26100,
    "tradeDate" : "2025-08-27",
    "closePrice" : 25750
  }, {
    "volume" : 413342,
    "marketCap" : 1391191160000,
    "lowPrice" : 25500,
    "highPrice" : 27700,
    "openPrice" : 25750,
    "tradeDate" : "2025-08-28",
    "closePrice" : 27400
  }, {
    "volume" : 260748,
    "marketCap" : 1416577860000,
    "lowPrice" : 27250,
    "highPrice" : 28050,
    "openPrice" : 27850,
    "tradeDate" : "2025-08-29",
    "closePrice" : 27900
  }, {
    "volume" : 340358,
    "marketCap" : 1388652490000,
    "lowPrice" : 27100,
    "highPrice" : 28600,
    "openPrice" : 27700,
    "tradeDate" : "2025-09-01",
    "closePrice" : 27350
  }, {
    "volume" : 204226,
    "marketCap" : 1383575150000,
    "lowPrice" : 26750,
    "highPrice" : 27500,
    "openPrice" : 27500,
    "tradeDate" : "2025-09-02",
    "closePrice" : 27250
  }, {
    "volume" : 210995,
    "marketCap" : 1393729830000,
    "lowPrice" : 26550,
    "highPrice" : 27450,
    "openPrice" : 27150,
    "tradeDate" : "2025-09-03",
    "closePrice" : 27450
  }, {
    "volume" : 163247,
    "marketCap" : 1383575150000,
    "lowPrice" : 26700,
    "highPrice" : 27500,
    "openPrice" : 27500,
    "tradeDate" : "2025-09-04",
    "closePrice" : 27250
  }, {
    "volume" : 83350,
    "marketCap" : 1368343130000,
    "lowPrice" : 26750,
    "highPrice" : 27450,
    "openPrice" : 27300,
    "tradeDate" : "2025-09-05",
    "closePrice" : 26950
  }, {
    "volume" : 171210,
    "marketCap" : 1386113820000,
    "lowPrice" : 26850,
    "highPrice" : 27500,
    "openPrice" : 27000,
    "tradeDate" : "2025-09-08",
    "closePrice" : 27300
  }, {
    "volume" : 584007,
    "marketCap" : 1469889930000,
    "lowPrice" : 27350,
    "highPrice" : 29000,
    "openPrice" : 27500,
    "tradeDate" : "2025-09-09",
    "closePrice" : 28950
  }, {
    "volume" : 532885,
    "marketCap" : 1467351260000,
    "lowPrice" : 28650,
    "highPrice" : 29275,
    "openPrice" : 29150,
    "tradeDate" : "2025-09-10",
    "closePrice" : 28900
  }, {
    "volume" : 390179,
    "marketCap" : 1459735250000,
    "lowPrice" : 27950,
    "highPrice" : 29150,
    "openPrice" : 28800,
    "tradeDate" : "2025-09-11",
    "closePrice" : 28750
  }, {
    "volume" : 191748,
    "marketCap" : 1459735250000,
    "lowPrice" : 28350,
    "highPrice" : 29150,
    "openPrice" : 29100,
    "tradeDate" : "2025-09-12",
    "closePrice" : 28750
  }, {
    "volume" : 427624,
    "marketCap" : 1454657910000,
    "lowPrice" : 28300,
    "highPrice" : 29500,
    "openPrice" : 28850,
    "tradeDate" : "2025-09-15",
    "closePrice" : 28650
  }, {
    "volume" : 250508,
    "marketCap" : 1429271210000,
    "lowPrice" : 28000,
    "highPrice" : 28750,
    "openPrice" : 28700,
    "tradeDate" : "2025-09-16",
    "closePrice" : 28150
  }, {
    "volume" : 198826,
    "marketCap" : 1421655200000,
    "lowPrice" : 27500,
    "highPrice" : 28250,
    "openPrice" : 28200,
    "tradeDate" : "2025-09-17",
    "closePrice" : 28000
  }, {
    "volume" : 179715,
    "marketCap" : 1421655200000,
    "lowPrice" : 27850,
    "highPrice" : 28400,
    "openPrice" : 28200,
    "tradeDate" : "2025-09-18",
    "closePrice" : 28000
  }, {
    "volume" : 136795,
    "marketCap" : 1426732540000,
    "lowPrice" : 27650,
    "highPrice" : 28100,
    "openPrice" : 27900,
    "tradeDate" : "2025-09-19",
    "closePrice" : 28100
  }, {
    "volume" : 189062,
    "marketCap" : 1429271210000,
    "lowPrice" : 27800,
    "highPrice" : 28300,
    "openPrice" : 28150,
    "tradeDate" : "2025-09-22",
    "closePrice" : 28150
  }, {
    "volume" : 185623,
    "marketCap" : 1411500520000,
    "lowPrice" : 27500,
    "highPrice" : 28300,
    "openPrice" : 28150,
    "tradeDate" : "2025-09-23",
    "closePrice" : 27800
  }, {
    "volume" : 466397,
    "marketCap" : 1355649780000,
    "lowPrice" : 26250,
    "highPrice" : 27700,
    "openPrice" : 27650,
    "tradeDate" : "2025-09-24",
    "closePrice" : 26700
  }, {
    "volume" : 303971,
    "marketCap" : 1327724410000,
    "lowPrice" : 26000,
    "highPrice" : 26550,
    "openPrice" : 26500,
    "tradeDate" : "2025-09-25",
    "closePrice" : 26150
  }, {
    "volume" : 178920,
    "marketCap" : 1327724410000,
    "lowPrice" : 25900,
    "highPrice" : 26550,
    "openPrice" : 26350,
    "tradeDate" : "2025-09-26",
    "closePrice" : 26150
  }, {
    "volume" : 210858,
    "marketCap" : 1363265790000,
    "lowPrice" : 26400,
    "highPrice" : 26950,
    "openPrice" : 26400,
    "tradeDate" : "2025-09-29",
    "closePrice" : 26850
  }, {
    "volume" : 169206,
    "marketCap" : 1340417760000,
    "lowPrice" : 26000,
    "highPrice" : 26850,
    "openPrice" : 26850,
    "tradeDate" : "2025-09-30",
    "closePrice" : 26400
  }, {
    "volume" : 173543,
    "marketCap" : 1315031060000,
    "lowPrice" : 25700,
    "highPrice" : 26450,
    "openPrice" : 26450,
    "tradeDate" : "2025-10-01",
    "closePrice" : 25900
  }, {
    "volume" : 237147,
    "marketCap" : 1353111110000,
    "lowPrice" : 25900,
    "highPrice" : 26700,
    "openPrice" : 26000,
    "tradeDate" : "2025-10-02",
    "closePrice" : 26650
  }, {
    "volume" : 166253,
    "marketCap" : 1363265790000,
    "lowPrice" : 26300,
    "highPrice" : 26900,
    "openPrice" : 26750,
    "tradeDate" : "2025-10-10",
    "closePrice" : 26850
  }, {
    "volume" : 144325,
    "marketCap" : 1358188450000,
    "lowPrice" : 25750,
    "highPrice" : 26750,
    "openPrice" : 26500,
    "tradeDate" : "2025-10-13",
    "closePrice" : 26750
  }, {
    "volume" : 137003,
    "marketCap" : 1335340420000,
    "lowPrice" : 25950,
    "highPrice" : 26800,
    "openPrice" : 26750,
    "tradeDate" : "2025-10-14",
    "closePrice" : 26300
  }, {
    "volume" : 156052,
    "marketCap" : 1350572440000,
    "lowPrice" : 26150,
    "highPrice" : 26750,
    "openPrice" : 26150,
    "tradeDate" : "2025-10-15",
    "closePrice" : 26600
  }, {
    "volume" : 302260,
    "marketCap" : 1388652490000,
    "lowPrice" : 26700,
    "highPrice" : 28000,
    "openPrice" : 26700,
    "tradeDate" : "2025-10-16",
    "closePrice" : 27350
  }, {
    "volume" : 820772,
    "marketCap" : 1355649780000,
    "lowPrice" : 26300,
    "highPrice" : 27300,
    "openPrice" : 27200,
    "tradeDate" : "2025-10-17",
    "closePrice" : 26700
  }, {
    "volume" : 490736,
    "marketCap" : 1452119240000,
    "lowPrice" : 26600,
    "highPrice" : 28600,
    "openPrice" : 26950,
    "tradeDate" : "2025-10-20",
    "closePrice" : 28600
  }, {
    "volume" : 391916,
    "marketCap" : 1421655200000,
    "lowPrice" : 27950,
    "highPrice" : 28950,
    "openPrice" : 28700,
    "tradeDate" : "2025-10-21",
    "closePrice" : 28000
  }, {
    "volume" : 230955,
    "marketCap" : 1431809880000,
    "lowPrice" : 27400,
    "highPrice" : 28250,
    "openPrice" : 28000,
    "tradeDate" : "2025-10-22",
    "closePrice" : 28200
  }, {
    "volume" : 175044,
    "marketCap" : 1434348550000,
    "lowPrice" : 27350,
    "highPrice" : 28250,
    "openPrice" : 28000,
    "tradeDate" : "2025-10-23",
    "closePrice" : 28250
  }, {
    "volume" : 486089,
    "marketCap" : 1469889930000,
    "lowPrice" : 28350,
    "highPrice" : 29500,
    "openPrice" : 28450,
    "tradeDate" : "2025-10-24",
    "closePrice" : 28950
  }, {
    "volume" : 438585,
    "marketCap" : 1462273920000,
    "lowPrice" : 28550,
    "highPrice" : 29800,
    "openPrice" : 29500,
    "tradeDate" : "2025-10-27",
    "closePrice" : 28800
  }, {
    "volume" : 206077,
    "marketCap" : 1444503230000,
    "lowPrice" : 28150,
    "highPrice" : 29050,
    "openPrice" : 28700,
    "tradeDate" : "2025-10-28",
    "closePrice" : 28450
  }, {
    "volume" : 182604,
    "marketCap" : 1459735250000,
    "lowPrice" : 28000,
    "highPrice" : 28900,
    "openPrice" : 28850,
    "tradeDate" : "2025-10-29",
    "closePrice" : 28750
  }, {
    "volume" : 391933,
    "marketCap" : 1464812590000,
    "lowPrice" : 28550,
    "highPrice" : 29750,
    "openPrice" : 28950,
    "tradeDate" : "2025-10-30",
    "closePrice" : 28850
  }, {
    "volume" : 274116,
    "marketCap" : 1477505940000,
    "lowPrice" : 28450,
    "highPrice" : 29550,
    "openPrice" : 28850,
    "tradeDate" : "2025-10-31",
    "closePrice" : 29100
  }, {
    "volume" : 400769,
    "marketCap" : 1518124660000,
    "lowPrice" : 28800,
    "highPrice" : 30400,
    "openPrice" : 29150,
    "tradeDate" : "2025-11-03",
    "closePrice" : 29900
  }, {
    "volume" : 475375,
    "marketCap" : 1436887220000,
    "lowPrice" : 28000,
    "highPrice" : 29850,
    "openPrice" : 29850,
    "tradeDate" : "2025-11-04",
    "closePrice" : 28300
  }, {
    "volume" : 293448,
    "marketCap" : 1411500520000,
    "lowPrice" : 26950,
    "highPrice" : 28050,
    "openPrice" : 28050,
    "tradeDate" : "2025-11-05",
    "closePrice" : 27800
  }, {
    "volume" : 265258,
    "marketCap" : 1449580570000,
    "lowPrice" : 27300,
    "highPrice" : 28900,
    "openPrice" : 28200,
    "tradeDate" : "2025-11-06",
    "closePrice" : 28550
  }, {
    "volume" : 254810,
    "marketCap" : 1411500520000,
    "lowPrice" : 27150,
    "highPrice" : 28500,
    "openPrice" : 28450,
    "tradeDate" : "2025-11-07",
    "closePrice" : 27800
  }, {
    "volume" : 339626,
    "marketCap" : 1462273920000,
    "lowPrice" : 28050,
    "highPrice" : 29050,
    "openPrice" : 28050,
    "tradeDate" : "2025-11-10",
    "closePrice" : 28800
  }, {
    "volume" : 297054,
    "marketCap" : 1431809880000,
    "lowPrice" : 28000,
    "highPrice" : 29250,
    "openPrice" : 28900,
    "tradeDate" : "2025-11-11",
    "closePrice" : 28200
  }, {
    "volume" : 763374,
    "marketCap" : 1530818010000,
    "lowPrice" : 28150,
    "highPrice" : 30300,
    "openPrice" : 28350,
    "tradeDate" : "2025-11-12",
    "closePrice" : 30150
  }, {
    "volume" : 299698,
    "marketCap" : 1520663330000,
    "lowPrice" : 29300,
    "highPrice" : 30100,
    "openPrice" : 29950,
    "tradeDate" : "2025-11-13",
    "closePrice" : 29950
  }, {
    "volume" : 347013,
    "marketCap" : 1467351260000,
    "lowPrice" : 28750,
    "highPrice" : 29900,
    "openPrice" : 29050,
    "tradeDate" : "2025-11-14",
    "closePrice" : 28900
  }, {
    "volume" : 354656,
    "marketCap" : 1477505940000,
    "lowPrice" : 28200,
    "highPrice" : 29450,
    "openPrice" : 29100,
    "tradeDate" : "2025-11-17",
    "closePrice" : 29100
  }, {
    "volume" : 344103,
    "marketCap" : 1391191160000,
    "lowPrice" : 27300,
    "highPrice" : 28800,
    "openPrice" : 28650,
    "tradeDate" : "2025-11-18",
    "closePrice" : 27400
  }, {
    "volume" : 222942,
    "marketCap" : 1378497810000,
    "lowPrice" : 26600,
    "highPrice" : 27750,
    "openPrice" : 27600,
    "tradeDate" : "2025-11-19",
    "closePrice" : 27150
  }, {
    "volume" : 214546,
    "marketCap" : 1398807170000,
    "lowPrice" : 27250,
    "highPrice" : 28050,
    "openPrice" : 27600,
    "tradeDate" : "2025-11-20",
    "closePrice" : 27550
  }, {
    "volume" : 213535,
    "marketCap" : 1375959140000,
    "lowPrice" : 26600,
    "highPrice" : 27250,
    "openPrice" : 26850,
    "tradeDate" : "2025-11-21",
    "closePrice" : 27100
  }, {
    "volume" : 267742,
    "marketCap" : 1345495100000,
    "lowPrice" : 26400,
    "highPrice" : 27200,
    "openPrice" : 27150,
    "tradeDate" : "2025-11-24",
    "closePrice" : 26500
  }, {
    "volume" : 180159,
    "marketCap" : 1325185740000,
    "lowPrice" : 25900,
    "highPrice" : 26900,
    "openPrice" : 26800,
    "tradeDate" : "2025-11-25",
    "closePrice" : 26100
  }, {
    "volume" : 157395,
    "marketCap" : 1353111110000,
    "lowPrice" : 26000,
    "highPrice" : 26700,
    "openPrice" : 26300,
    "tradeDate" : "2025-11-26",
    "closePrice" : 26650
  }, {
    "volume" : 138847,
    "marketCap" : 1373420470000,
    "lowPrice" : 26600,
    "highPrice" : 27200,
    "openPrice" : 26700,
    "tradeDate" : "2025-11-27",
    "closePrice" : 27050
  }, {
    "volume" : 118236,
    "marketCap" : 1375959140000,
    "lowPrice" : 26800,
    "highPrice" : 27200,
    "openPrice" : 27150,
    "tradeDate" : "2025-11-28",
    "closePrice" : 27100
  }, {
    "volume" : 107012,
    "marketCap" : 1375959140000,
    "lowPrice" : 26800,
    "highPrice" : 27600,
    "openPrice" : 27250,
    "tradeDate" : "2025-12-01",
    "closePrice" : 27100
  }, {
    "volume" : 156773,
    "marketCap" : 1396268500000,
    "lowPrice" : 26900,
    "highPrice" : 27700,
    "openPrice" : 27100,
    "tradeDate" : "2025-12-02",
    "closePrice" : 27500
  }, {
    "volume" : 268671,
    "marketCap" : 1431809880000,
    "lowPrice" : 27400,
    "highPrice" : 28750,
    "openPrice" : 27500,
    "tradeDate" : "2025-12-03",
    "closePrice" : 28200
  }, {
    "volume" : 96420,
    "marketCap" : 1421655200000,
    "lowPrice" : 27800,
    "highPrice" : 28300,
    "openPrice" : 28250,
    "tradeDate" : "2025-12-04",
    "closePrice" : 28000
  }, {
    "volume" : 96034,
    "marketCap" : 1436887220000,
    "lowPrice" : 27600,
    "highPrice" : 28350,
    "openPrice" : 27950,
    "tradeDate" : "2025-12-05",
    "closePrice" : 28300
  }, {
    "volume" : 134025,
    "marketCap" : 1416577860000,
    "lowPrice" : 27600,
    "highPrice" : 28650,
    "openPrice" : 28350,
    "tradeDate" : "2025-12-08",
    "closePrice" : 27900
  }, {
    "volume" : 129107,
    "marketCap" : 1396268500000,
    "lowPrice" : 27250,
    "highPrice" : 27850,
    "openPrice" : 27800,
    "tradeDate" : "2025-12-09",
    "closePrice" : 27500
  }, {
    "volume" : 170056,
    "marketCap" : 1360727120000,
    "lowPrice" : 26750,
    "highPrice" : 27600,
    "openPrice" : 27500,
    "tradeDate" : "2025-12-10",
    "closePrice" : 26800
  }, {
    "volume" : 170298,
    "marketCap" : 1355649780000,
    "lowPrice" : 26500,
    "highPrice" : 27150,
    "openPrice" : 26900,
    "tradeDate" : "2025-12-11",
    "closePrice" : 26700
  }, {
    "volume" : 677679,
    "marketCap" : 1444503230000,
    "lowPrice" : 26700,
    "highPrice" : 28650,
    "openPrice" : 26750,
    "tradeDate" : "2025-12-12",
    "closePrice" : 28450
  }, {
    "volume" : 170245,
    "marketCap" : 1393729830000,
    "lowPrice" : 27350,
    "highPrice" : 28100,
    "openPrice" : 27600,
    "tradeDate" : "2025-12-15",
    "closePrice" : 27450
  }, {
    "volume" : 161074,
    "marketCap" : 1393729830000,
    "lowPrice" : 27150,
    "highPrice" : 27950,
    "openPrice" : 27450,
    "tradeDate" : "2025-12-16",
    "closePrice" : 27450
  }, {
    "volume" : 96298,
    "marketCap" : 1381036480000,
    "lowPrice" : 26950,
    "highPrice" : 27750,
    "openPrice" : 27750,
    "tradeDate" : "2025-12-17",
    "closePrice" : 27200
  }, {
    "volume" : 73673,
    "marketCap" : 1383575150000,
    "lowPrice" : 26750,
    "highPrice" : 27400,
    "openPrice" : 26900,
    "tradeDate" : "2025-12-18",
    "closePrice" : 27250
  }, {
    "volume" : 137335,
    "marketCap" : 1386113820000,
    "lowPrice" : 27150,
    "highPrice" : 27750,
    "openPrice" : 27300,
    "tradeDate" : "2025-12-19",
    "closePrice" : 27300
  }, {
    "volume" : 104496,
    "marketCap" : 1393729830000,
    "lowPrice" : 27300,
    "highPrice" : 27800,
    "openPrice" : 27500,
    "tradeDate" : "2025-12-22",
    "closePrice" : 27450
  } ],
  "stockCode" : "003540"
}