{
  "lastUpdated" : "2025-12-23",
  "stockName" : "한화투자증권",
  "prices" : [ {
    "volume" : 2387887,
    "marketCap" : 749844473625,
    "lowPrice" : 3405,
    "highPrice" : 3560,
    "openPrice" : 3440,
    "tradeDate" : "2024-12-23",
    "closePrice" : 3495
  }, {
    "volume" : 1332793,
    "marketCap" : 744480779250,
    "lowPrice" : 3440,
    "highPrice" : 3520,
    "openPrice" : 3470,
    "tradeDate" : "2024-12-24",
    "closePrice" : 3470
  }, {
    "volume" : 1948568,
    "marketCap" : 757353645750,
    "lowPrice" : 3490,
    "highPrice" : 3575,
    "openPrice" : 3545,
    "tradeDate" : "2024-12-26",
    "closePrice" : 3530
  }, {
    "volume" : 1426234,
    "marketCap" : 744480779250,
    "lowPrice" : 3390,
    "highPrice" : 3495,
    "openPrice" : 3465,
    "tradeDate" : "2024-12-27",
    "closePrice" : 3470
  }, {
    "volume" : 1527103,
    "marketCap" : 720880524000,
    "lowPrice" : 3350,
    "highPrice" : 3440,
    "openPrice" : 3400,
    "tradeDate" : "2024-12-30",
    "closePrice" : 3360
  }, {
    "volume" : 1246141,
    "marketCap" : 747698995875,
    "lowPrice" : 3400,
    "highPrice" : 3495,
    "openPrice" : 3400,
    "tradeDate" : "2025-01-02",
    "closePrice" : 3485
  }, {
    "volume" : 2236259,
    "marketCap" : 767008295625,
    "lowPrice" : 3495,
    "highPrice" : 3610,
    "openPrice" : 3505,
    "tradeDate" : "2025-01-03",
    "closePrice" : 3575
  }, {
    "volume" : 2568370,
    "marketCap" : 797044984125,
    "lowPrice" : 3580,
    "highPrice" : 3755,
    "openPrice" : 3610,
    "tradeDate" : "2025-01-06",
    "closePrice" : 3715
  }, {
    "volume" : 2018210,
    "marketCap" : 787390334250,
    "lowPrice" : 3650,
    "highPrice" : 3815,
    "openPrice" : 3815,
    "tradeDate" : "2025-01-07",
    "closePrice" : 3670
  }, {
    "volume" : 1420696,
    "marketCap" : 787390334250,
    "lowPrice" : 3565,
    "highPrice" : 3730,
    "openPrice" : 3580,
    "tradeDate" : "2025-01-08",
    "closePrice" : 3670
  }, {
    "volume" : 1062766,
    "marketCap" : 790608550875,
    "lowPrice" : 3615,
    "highPrice" : 3710,
    "openPrice" : 3670,
    "tradeDate" : "2025-01-09",
    "closePrice" : 3685
  }, {
    "volume" : 1499495,
    "marketCap" : 795972245250,
    "lowPrice" : 3610,
    "highPrice" : 3750,
    "openPrice" : 3640,
    "tradeDate" : "2025-01-10",
    "closePrice" : 3710
  }, {
    "volume" : 625212,
    "marketCap" : 784172117625,
    "lowPrice" : 3640,
    "highPrice" : 3725,
    "openPrice" : 3685,
    "tradeDate" : "2025-01-13",
    "closePrice" : 3655
  }, {
    "volume" : 933462,
    "marketCap" : 793826767500,
    "lowPrice" : 3625,
    "highPrice" : 3720,
    "openPrice" : 3660,
    "tradeDate" : "2025-01-14",
    "closePrice" : 3700
  }, {
    "volume" : 802508,
    "marketCap" : 797044984125,
    "lowPrice" : 3700,
    "highPrice" : 3760,
    "openPrice" : 3735,
    "tradeDate" : "2025-01-15",
    "closePrice" : 3715
  }, {
    "volume" : 1172703,
    "marketCap" : 795972245250,
    "lowPrice" : 3695,
    "highPrice" : 3795,
    "openPrice" : 3795,
    "tradeDate" : "2025-01-16",
    "closePrice" : 3710
  }, {
    "volume" : 1948908,
    "marketCap" : 812063328375,
    "lowPrice" : 3625,
    "highPrice" : 3810,
    "openPrice" : 3630,
    "tradeDate" : "2025-01-17",
    "closePrice" : 3785
  }, {
    "volume" : 1607744,
    "marketCap" : 809917850625,
    "lowPrice" : 3750,
    "highPrice" : 3830,
    "openPrice" : 3825,
    "tradeDate" : "2025-01-20",
    "closePrice" : 3775
  }, {
    "volume" : 1232899,
    "marketCap" : 801335939625,
    "lowPrice" : 3710,
    "highPrice" : 3810,
    "openPrice" : 3760,
    "tradeDate" : "2025-01-21",
    "closePrice" : 3735
  }, {
    "volume" : 723038,
    "marketCap" : 805626895125,
    "lowPrice" : 3740,
    "highPrice" : 3810,
    "openPrice" : 3770,
    "tradeDate" : "2025-01-22",
    "closePrice" : 3755
  }, {
    "volume" : 983856,
    "marketCap" : 772371990000,
    "lowPrice" : 3580,
    "highPrice" : 3730,
    "openPrice" : 3730,
    "tradeDate" : "2025-01-23",
    "closePrice" : 3600
  }, {
    "volume" : 1070858,
    "marketCap" : 768081034500,
    "lowPrice" : 3565,
    "highPrice" : 3660,
    "openPrice" : 3630,
    "tradeDate" : "2025-01-24",
    "closePrice" : 3580
  }, {
    "volume" : 793566,
    "marketCap" : 774517467750,
    "lowPrice" : 3565,
    "highPrice" : 3645,
    "openPrice" : 3580,
    "tradeDate" : "2025-01-31",
    "closePrice" : 3610
  }, {
    "volume" : 1387400,
    "marketCap" : 730535173875,
    "lowPrice" : 3390,
    "highPrice" : 3495,
    "openPrice" : 3495,
    "tradeDate" : "2025-02-03",
    "closePrice" : 3405
  }, {
    "volume" : 935363,
    "marketCap" : 738044346000,
    "lowPrice" : 3435,
    "highPrice" : 3535,
    "openPrice" : 3490,
    "tradeDate" : "2025-02-04",
    "closePrice" : 3440
  }, {
    "volume" : 781581,
    "marketCap" : 734826129375,
    "lowPrice" : 3415,
    "highPrice" : 3460,
    "openPrice" : 3440,
    "tradeDate" : "2025-02-05",
    "closePrice" : 3425
  }, {
    "volume" : 1852425,
    "marketCap" : 724098740625,
    "lowPrice" : 3355,
    "highPrice" : 3445,
    "openPrice" : 3430,
    "tradeDate" : "2025-02-06",
    "closePrice" : 3375
  }, {
    "volume" : 1182748,
    "marketCap" : 711225874125,
    "lowPrice" : 3305,
    "highPrice" : 3380,
    "openPrice" : 3355,
    "tradeDate" : "2025-02-07",
    "closePrice" : 3315
  }, {
    "volume" : 658132,
    "marketCap" : 713371351875,
    "lowPrice" : 3280,
    "highPrice" : 3345,
    "openPrice" : 3305,
    "tradeDate" : "2025-02-10",
    "closePrice" : 3325
  }, {
    "volume" : 637930,
    "marketCap" : 717662307375,
    "lowPrice" : 3325,
    "highPrice" : 3380,
    "openPrice" : 3330,
    "tradeDate" : "2025-02-11",
    "closePrice" : 3345
  }, {
    "volume" : 1222589,
    "marketCap" : 739117084875,
    "lowPrice" : 3305,
    "highPrice" : 3455,
    "openPrice" : 3345,
    "tradeDate" : "2025-02-12",
    "closePrice" : 3445
  }, {
    "volume" : 3519466,
    "marketCap" : 777735684375,
    "lowPrice" : 3450,
    "highPrice" : 3645,
    "openPrice" : 3450,
    "tradeDate" : "2025-02-13",
    "closePrice" : 3625
  }, {
    "volume" : 2886736,
    "marketCap" : 791681289750,
    "lowPrice" : 3620,
    "highPrice" : 3765,
    "openPrice" : 3660,
    "tradeDate" : "2025-02-14",
    "closePrice" : 3690
  }, {
    "volume" : 3800426,
    "marketCap" : 827081672625,
    "lowPrice" : 3650,
    "highPrice" : 3870,
    "openPrice" : 3690,
    "tradeDate" : "2025-02-17",
    "closePrice" : 3855
  }, {
    "volume" : 1920346,
    "marketCap" : 813136067250,
    "lowPrice" : 3730,
    "highPrice" : 3875,
    "openPrice" : 3870,
    "tradeDate" : "2025-02-18",
    "closePrice" : 3790
  }, {
    "volume" : 1612084,
    "marketCap" : 805626895125,
    "lowPrice" : 3725,
    "highPrice" : 3805,
    "openPrice" : 3770,
    "tradeDate" : "2025-02-19",
    "closePrice" : 3755
  }, {
    "volume" : 1087445,
    "marketCap" : 799190461875,
    "lowPrice" : 3695,
    "highPrice" : 3815,
    "openPrice" : 3765,
    "tradeDate" : "2025-02-20",
    "closePrice" : 3725
  }, {
    "volume" : 1150598,
    "marketCap" : 775590206625,
    "lowPrice" : 3600,
    "highPrice" : 3705,
    "openPrice" : 3705,
    "tradeDate" : "2025-02-21",
    "closePrice" : 3615
  }, {
    "volume" : 1003268,
    "marketCap" : 756280906875,
    "lowPrice" : 3500,
    "highPrice" : 3575,
    "openPrice" : 3560,
    "tradeDate" : "2025-02-24",
    "closePrice" : 3525
  }, {
    "volume" : 1098657,
    "marketCap" : 760571862375,
    "lowPrice" : 3470,
    "highPrice" : 3650,
    "openPrice" : 3500,
    "tradeDate" : "2025-02-25",
    "closePrice" : 3545
  }, {
    "volume" : 548425,
    "marketCap" : 763790079000,
    "lowPrice" : 3515,
    "highPrice" : 3595,
    "openPrice" : 3525,
    "tradeDate" : "2025-02-26",
    "closePrice" : 3560
  }, {
    "volume" : 639652,
    "marketCap" : 757353645750,
    "lowPrice" : 3500,
    "highPrice" : 3555,
    "openPrice" : 3540,
    "tradeDate" : "2025-02-27",
    "closePrice" : 3530
  }, {
    "volume" : 1004381,
    "marketCap" : 738044346000,
    "lowPrice" : 3420,
    "highPrice" : 3490,
    "openPrice" : 3485,
    "tradeDate" : "2025-02-28",
    "closePrice" : 3440
  }, {
    "volume" : 1202446,
    "marketCap" : 756280906875,
    "lowPrice" : 3450,
    "highPrice" : 3595,
    "openPrice" : 3505,
    "tradeDate" : "2025-03-04",
    "closePrice" : 3525
  }, {
    "volume" : 1318093,
    "marketCap" : 782026639875,
    "lowPrice" : 3520,
    "highPrice" : 3650,
    "openPrice" : 3520,
    "tradeDate" : "2025-03-05",
    "closePrice" : 3645
  }, {
    "volume" : 839911,
    "marketCap" : 773444728875,
    "lowPrice" : 3595,
    "highPrice" : 3675,
    "openPrice" : 3675,
    "tradeDate" : "2025-03-06",
    "closePrice" : 3605
  }, {
    "volume" : 845108,
    "marketCap" : 761644601250,
    "lowPrice" : 3545,
    "highPrice" : 3650,
    "openPrice" : 3590,
    "tradeDate" : "2025-03-07",
    "closePrice" : 3550
  }, {
    "volume" : 994382,
    "marketCap" : 743408040375,
    "lowPrice" : 3420,
    "highPrice" : 3545,
    "openPrice" : 3505,
    "tradeDate" : "2025-03-10",
    "closePrice" : 3465
  }, {
    "volume" : 1075183,
    "marketCap" : 731607912750,
    "lowPrice" : 3355,
    "highPrice" : 3420,
    "openPrice" : 3400,
    "tradeDate" : "2025-03-11",
    "closePrice" : 3410
  }, {
    "volume" : 571110,
    "marketCap" : 750917212500,
    "lowPrice" : 3425,
    "highPrice" : 3525,
    "openPrice" : 3425,
    "tradeDate" : "2025-03-12",
    "closePrice" : 3500
  }, {
    "volume" : 748605,
    "marketCap" : 746626257000,
    "lowPrice" : 3475,
    "highPrice" : 3550,
    "openPrice" : 3505,
    "tradeDate" : "2025-03-13",
    "closePrice" : 3480
  }, {
    "volume" : 518134,
    "marketCap" : 736971607125,
    "lowPrice" : 3435,
    "highPrice" : 3500,
    "openPrice" : 3500,
    "tradeDate" : "2025-03-14",
    "closePrice" : 3435
  }, {
    "volume" : 658528,
    "marketCap" : 747698995875,
    "lowPrice" : 3435,
    "highPrice" : 3485,
    "openPrice" : 3445,
    "tradeDate" : "2025-03-17",
    "closePrice" : 3485
  }, {
    "volume" : 469552,
    "marketCap" : 745553518125,
    "lowPrice" : 3470,
    "highPrice" : 3510,
    "openPrice" : 3490,
    "tradeDate" : "2025-03-18",
    "closePrice" : 3475
  }, {
    "volume" : 509411,
    "marketCap" : 749844473625,
    "lowPrice" : 3450,
    "highPrice" : 3500,
    "openPrice" : 3455,
    "tradeDate" : "2025-03-19",
    "closePrice" : 3495
  }, {
    "volume" : 788525,
    "marketCap" : 748771734750,
    "lowPrice" : 3485,
    "highPrice" : 3575,
    "openPrice" : 3530,
    "tradeDate" : "2025-03-20",
    "closePrice" : 3490
  }, {
    "volume" : 546586,
    "marketCap" : 740189823750,
    "lowPrice" : 3425,
    "highPrice" : 3490,
    "openPrice" : 3455,
    "tradeDate" : "2025-03-21",
    "closePrice" : 3450
  }, {
    "volume" : 468569,
    "marketCap" : 747698995875,
    "lowPrice" : 3460,
    "highPrice" : 3520,
    "openPrice" : 3475,
    "tradeDate" : "2025-03-24",
    "closePrice" : 3485
  }, {
    "volume" : 485477,
    "marketCap" : 736971607125,
    "lowPrice" : 3420,
    "highPrice" : 3530,
    "openPrice" : 3515,
    "tradeDate" : "2025-03-25",
    "closePrice" : 3435
  }, {
    "volume" : 297225,
    "marketCap" : 736971607125,
    "lowPrice" : 3415,
    "highPrice" : 3460,
    "openPrice" : 3440,
    "tradeDate" : "2025-03-26",
    "closePrice" : 3435
  }, {
    "volume" : 519128,
    "marketCap" : 724098740625,
    "lowPrice" : 3375,
    "highPrice" : 3430,
    "openPrice" : 3405,
    "tradeDate" : "2025-03-27",
    "closePrice" : 3375
  }, {
    "volume" : 519867,
    "marketCap" : 714444090750,
    "lowPrice" : 3320,
    "highPrice" : 3390,
    "openPrice" : 3370,
    "tradeDate" : "2025-03-28",
    "closePrice" : 3330
  }, {
    "volume" : 943248,
    "marketCap" : 677970969000,
    "lowPrice" : 3150,
    "highPrice" : 3290,
    "openPrice" : 3290,
    "tradeDate" : "2025-03-31",
    "closePrice" : 3160
  }, {
    "volume" : 383556,
    "marketCap" : 705862179750,
    "lowPrice" : 3195,
    "highPrice" : 3300,
    "openPrice" : 3205,
    "tradeDate" : "2025-04-01",
    "closePrice" : 3290
  }, {
    "volume" : 258682,
    "marketCap" : 691916574375,
    "lowPrice" : 3220,
    "highPrice" : 3315,
    "openPrice" : 3305,
    "tradeDate" : "2025-04-02",
    "closePrice" : 3225
  }, {
    "volume" : 444331,
    "marketCap" : 680116446750,
    "lowPrice" : 3115,
    "highPrice" : 3175,
    "openPrice" : 3155,
    "tradeDate" : "2025-04-03",
    "closePrice" : 3170
  }, {
    "volume" : 484307,
    "marketCap" : 689771096625,
    "lowPrice" : 3100,
    "highPrice" : 3245,
    "openPrice" : 3100,
    "tradeDate" : "2025-04-04",
    "closePrice" : 3215
  }, {
    "volume" : 1097045,
    "marketCap" : 635061414000,
    "lowPrice" : 2945,
    "highPrice" : 3115,
    "openPrice" : 3105,
    "tradeDate" : "2025-04-07",
    "closePrice" : 2960
  }, {
    "volume" : 603483,
    "marketCap" : 643643325000,
    "lowPrice" : 2985,
    "highPrice" : 3075,
    "openPrice" : 3020,
    "tradeDate" : "2025-04-08",
    "closePrice" : 3000
  }, {
    "volume" : 717813,
    "marketCap" : 632915936250,
    "lowPrice" : 2910,
    "highPrice" : 3025,
    "openPrice" : 2965,
    "tradeDate" : "2025-04-09",
    "closePrice" : 2950
  }, {
    "volume" : 392591,
    "marketCap" : 665098102500,
    "lowPrice" : 3070,
    "highPrice" : 3125,
    "openPrice" : 3100,
    "tradeDate" : "2025-04-10",
    "closePrice" : 3100
  }, {
    "volume" : 315771,
    "marketCap" : 675825491250,
    "lowPrice" : 3040,
    "highPrice" : 3155,
    "openPrice" : 3055,
    "tradeDate" : "2025-04-11",
    "closePrice" : 3150
  }, {
    "volume" : 209327,
    "marketCap" : 680116446750,
    "lowPrice" : 3150,
    "highPrice" : 3195,
    "openPrice" : 3190,
    "tradeDate" : "2025-04-14",
    "closePrice" : 3170
  }, {
    "volume" : 226968,
    "marketCap" : 686552880000,
    "lowPrice" : 3165,
    "highPrice" : 3225,
    "openPrice" : 3195,
    "tradeDate" : "2025-04-15",
    "closePrice" : 3200
  }, {
    "volume" : 351836,
    "marketCap" : 681189185625,
    "lowPrice" : 3150,
    "highPrice" : 3215,
    "openPrice" : 3205,
    "tradeDate" : "2025-04-16",
    "closePrice" : 3175
  }, {
    "volume" : 133979,
    "marketCap" : 681189185625,
    "lowPrice" : 3155,
    "highPrice" : 3200,
    "openPrice" : 3155,
    "tradeDate" : "2025-04-17",
    "closePrice" : 3175
  }, {
    "volume" : 284117,
    "marketCap" : 689771096625,
    "lowPrice" : 3155,
    "highPrice" : 3215,
    "openPrice" : 3195,
    "tradeDate" : "2025-04-18",
    "closePrice" : 3215
  }, {
    "volume" : 567451,
    "marketCap" : 702643963125,
    "lowPrice" : 3225,
    "highPrice" : 3295,
    "openPrice" : 3285,
    "tradeDate" : "2025-04-21",
    "closePrice" : 3275
  }, {
    "volume" : 381163,
    "marketCap" : 701571224250,
    "lowPrice" : 3255,
    "highPrice" : 3300,
    "openPrice" : 3260,
    "tradeDate" : "2025-04-22",
    "closePrice" : 3270
  }, {
    "volume" : 587943,
    "marketCap" : 716589568500,
    "lowPrice" : 3305,
    "highPrice" : 3370,
    "openPrice" : 3360,
    "tradeDate" : "2025-04-23",
    "closePrice" : 3340
  }, {
    "volume" : 192527,
    "marketCap" : 710153135250,
    "lowPrice" : 3290,
    "highPrice" : 3355,
    "openPrice" : 3350,
    "tradeDate" : "2025-04-24",
    "closePrice" : 3310
  }, {
    "volume" : 378202,
    "marketCap" : 719807785125,
    "lowPrice" : 3330,
    "highPrice" : 3375,
    "openPrice" : 3340,
    "tradeDate" : "2025-04-25",
    "closePrice" : 3355
  }, {
    "volume" : 322011,
    "marketCap" : 723026001750,
    "lowPrice" : 3345,
    "highPrice" : 3385,
    "openPrice" : 3355,
    "tradeDate" : "2025-04-28",
    "closePrice" : 3370
  }, {
    "volume" : 573846,
    "marketCap" : 735898868250,
    "lowPrice" : 3355,
    "highPrice" : 3440,
    "openPrice" : 3375,
    "tradeDate" : "2025-04-29",
    "closePrice" : 3430
  }, {
    "volume" : 996649,
    "marketCap" : 736971607125,
    "lowPrice" : 3405,
    "highPrice" : 3515,
    "openPrice" : 3415,
    "tradeDate" : "2025-04-30",
    "closePrice" : 3435
  }, {
    "volume" : 1372259,
    "marketCap" : 744480779250,
    "lowPrice" : 3430,
    "highPrice" : 3540,
    "openPrice" : 3480,
    "tradeDate" : "2025-05-02",
    "closePrice" : 3470
  }, {
    "volume" : 419403,
    "marketCap" : 749844473625,
    "lowPrice" : 3450,
    "highPrice" : 3500,
    "openPrice" : 3475,
    "tradeDate" : "2025-05-07",
    "closePrice" : 3495
  }, {
    "volume" : 569925,
    "marketCap" : 761644601250,
    "lowPrice" : 3485,
    "highPrice" : 3550,
    "openPrice" : 3535,
    "tradeDate" : "2025-05-08",
    "closePrice" : 3550
  }, {
    "volume" : 1288300,
    "marketCap" : 768081034500,
    "lowPrice" : 3555,
    "highPrice" : 3675,
    "openPrice" : 3675,
    "tradeDate" : "2025-05-09",
    "closePrice" : 3580
  }, {
    "volume" : 1496446,
    "marketCap" : 791681289750,
    "lowPrice" : 3605,
    "highPrice" : 3735,
    "openPrice" : 3620,
    "tradeDate" : "2025-05-12",
    "closePrice" : 3690
  }, {
    "volume" : 602634,
    "marketCap" : 792754028625,
    "lowPrice" : 3622,
    "highPrice" : 3700,
    "openPrice" : 3700,
    "tradeDate" : "2025-05-13",
    "closePrice" : 3695
  }, {
    "volume" : 1507578,
    "marketCap" : 808845111750,
    "lowPrice" : 3750,
    "highPrice" : 3810,
    "openPrice" : 3795,
    "tradeDate" : "2025-05-14",
    "closePrice" : 3770
  }, {
    "volume" : 1243816,
    "marketCap" : 816354283875,
    "lowPrice" : 3770,
    "highPrice" : 3860,
    "openPrice" : 3830,
    "tradeDate" : "2025-05-15",
    "closePrice" : 3805
  }, {
    "volume" : 4319866,
    "marketCap" : 875354922000,
    "lowPrice" : 3835,
    "highPrice" : 4115,
    "openPrice" : 3835,
    "tradeDate" : "2025-05-16",
    "closePrice" : 4080
  }, {
    "volume" : 2389772,
    "marketCap" : 830299889250,
    "lowPrice" : 3780,
    "highPrice" : 4150,
    "openPrice" : 4130,
    "tradeDate" : "2025-05-19",
    "closePrice" : 3870
  }, {
    "volume" : 1285635,
    "marketCap" : 839954539125,
    "lowPrice" : 3880,
    "highPrice" : 4020,
    "openPrice" : 3930,
    "tradeDate" : "2025-05-20",
    "closePrice" : 3915
  }, {
    "volume" : 2319349,
    "marketCap" : 876427660875,
    "lowPrice" : 3885,
    "highPrice" : 4105,
    "openPrice" : 3945,
    "tradeDate" : "2025-05-21",
    "closePrice" : 4085
  }, {
    "volume" : 3218590,
    "marketCap" : 898955177250,
    "lowPrice" : 4105,
    "highPrice" : 4285,
    "openPrice" : 4255,
    "tradeDate" : "2025-05-22",
    "closePrice" : 4190
  }, {
    "volume" : 2738655,
    "marketCap" : 923628171375,
    "lowPrice" : 4100,
    "highPrice" : 4375,
    "openPrice" : 4260,
    "tradeDate" : "2025-05-23",
    "closePrice" : 4305
  }, {
    "volume" : 1631621,
    "marketCap" : 908609827125,
    "lowPrice" : 4155,
    "highPrice" : 4290,
    "openPrice" : 4290,
    "tradeDate" : "2025-05-26",
    "closePrice" : 4235
  }, {
    "volume" : 1682089,
    "marketCap" : 879645877500,
    "lowPrice" : 4045,
    "highPrice" : 4250,
    "openPrice" : 4245,
    "tradeDate" : "2025-05-27",
    "closePrice" : 4100
  }, {
    "volume" : 1374063,
    "marketCap" : 894664221750,
    "lowPrice" : 4100,
    "highPrice" : 4255,
    "openPrice" : 4145,
    "tradeDate" : "2025-05-28",
    "closePrice" : 4170
  }, {
    "volume" : 5289330,
    "marketCap" : 969755943000,
    "lowPrice" : 4190,
    "highPrice" : 4560,
    "openPrice" : 4215,
    "tradeDate" : "2025-05-29",
    "closePrice" : 4520
  }, {
    "volume" : 2992411,
    "marketCap" : 956883076500,
    "lowPrice" : 4365,
    "highPrice" : 4690,
    "openPrice" : 4690,
    "tradeDate" : "2025-05-30",
    "closePrice" : 4460
  }, {
    "volume" : 2312820,
    "marketCap" : 937573776750,
    "lowPrice" : 4305,
    "highPrice" : 4570,
    "openPrice" : 4520,
    "tradeDate" : "2025-06-02",
    "closePrice" : 4370
  }, {
    "volume" : 6429290,
    "marketCap" : 1027683842250,
    "lowPrice" : 4495,
    "highPrice" : 4800,
    "openPrice" : 4500,
    "tradeDate" : "2025-06-04",
    "closePrice" : 4790
  }, {
    "volume" : 3769120,
    "marketCap" : 1042702186500,
    "lowPrice" : 4590,
    "highPrice" : 4865,
    "openPrice" : 4825,
    "tradeDate" : "2025-06-05",
    "closePrice" : 4860
  }, {
    "volume" : 6661668,
    "marketCap" : 1139248685250,
    "lowPrice" : 4955,
    "highPrice" : 5430,
    "openPrice" : 5010,
    "tradeDate" : "2025-06-09",
    "closePrice" : 5310
  }, {
    "volume" : 5065430,
    "marketCap" : 1164994418250,
    "lowPrice" : 5200,
    "highPrice" : 5520,
    "openPrice" : 5510,
    "tradeDate" : "2025-06-10",
    "closePrice" : 5430
  }, {
    "volume" : 3724789,
    "marketCap" : 1192885629000,
    "lowPrice" : 5270,
    "highPrice" : 5620,
    "openPrice" : 5360,
    "tradeDate" : "2025-06-11",
    "closePrice" : 5560
  }, {
    "volume" : 18072335,
    "marketCap" : 1362378371250,
    "lowPrice" : 5510,
    "highPrice" : 6800,
    "openPrice" : 5540,
    "tradeDate" : "2025-06-12",
    "closePrice" : 6350
  }, {
    "volume" : 5753295,
    "marketCap" : 1289432127750,
    "lowPrice" : 5860,
    "highPrice" : 6380,
    "openPrice" : 6290,
    "tradeDate" : "2025-06-13",
    "closePrice" : 6010
  }, {
    "volume" : 4018430,
    "marketCap" : 1332341682750,
    "lowPrice" : 5900,
    "highPrice" : 6250,
    "openPrice" : 5930,
    "tradeDate" : "2025-06-16",
    "closePrice" : 6210
  }, {
    "volume" : 12874305,
    "marketCap" : 1437470092500,
    "lowPrice" : 6310,
    "highPrice" : 7060,
    "openPrice" : 6800,
    "tradeDate" : "2025-06-17",
    "closePrice" : 6700
  }, {
    "volume" : 6362139,
    "marketCap" : 1484670603000,
    "lowPrice" : 6580,
    "highPrice" : 7050,
    "openPrice" : 6670,
    "tradeDate" : "2025-06-18",
    "closePrice" : 6920
  }, {
    "volume" : 5478993,
    "marketCap" : 1480379647500,
    "lowPrice" : 6680,
    "highPrice" : 7300,
    "openPrice" : 7230,
    "tradeDate" : "2025-06-19",
    "closePrice" : 6900
  }, {
    "volume" : 3120440,
    "marketCap" : 1469652258750,
    "lowPrice" : 6680,
    "highPrice" : 6900,
    "openPrice" : 6810,
    "tradeDate" : "2025-06-20",
    "closePrice" : 6850
  }, {
    "volume" : 5978881,
    "marketCap" : 1448197481250,
    "lowPrice" : 6390,
    "highPrice" : 6970,
    "openPrice" : 6500,
    "tradeDate" : "2025-06-23",
    "closePrice" : 6750
  }, {
    "volume" : 5140843,
    "marketCap" : 1469652258750,
    "lowPrice" : 6720,
    "highPrice" : 7230,
    "openPrice" : 7050,
    "tradeDate" : "2025-06-24",
    "closePrice" : 6850
  }, {
    "volume" : 3057987,
    "marketCap" : 1465361303250,
    "lowPrice" : 6580,
    "highPrice" : 6890,
    "openPrice" : 6870,
    "tradeDate" : "2025-06-25",
    "closePrice" : 6830
  }, {
    "volume" : 4878566,
    "marketCap" : 1458924870000,
    "lowPrice" : 6350,
    "highPrice" : 6900,
    "openPrice" : 6730,
    "tradeDate" : "2025-06-26",
    "closePrice" : 6800
  }, {
    "volume" : 3026460,
    "marketCap" : 1441761048000,
    "lowPrice" : 6670,
    "highPrice" : 6980,
    "openPrice" : 6900,
    "tradeDate" : "2025-06-27",
    "closePrice" : 6720
  }, {
    "volume" : 2557112,
    "marketCap" : 1418160792750,
    "lowPrice" : 6560,
    "highPrice" : 6770,
    "openPrice" : 6690,
    "tradeDate" : "2025-06-30",
    "closePrice" : 6610
  }, {
    "volume" : 3635330,
    "marketCap" : 1461070347750,
    "lowPrice" : 6740,
    "highPrice" : 6940,
    "openPrice" : 6760,
    "tradeDate" : "2025-07-01",
    "closePrice" : 6810
  }, {
    "volume" : 4482945,
    "marketCap" : 1426742703750,
    "lowPrice" : 6590,
    "highPrice" : 7140,
    "openPrice" : 7120,
    "tradeDate" : "2025-07-02",
    "closePrice" : 6650
  }, {
    "volume" : 2972451,
    "marketCap" : 1396706015250,
    "lowPrice" : 6390,
    "highPrice" : 6710,
    "openPrice" : 6670,
    "tradeDate" : "2025-07-03",
    "closePrice" : 6510
  }, {
    "volume" : 2442497,
    "marketCap" : 1340923593750,
    "lowPrice" : 6230,
    "highPrice" : 6620,
    "openPrice" : 6520,
    "tradeDate" : "2025-07-04",
    "closePrice" : 6250
  }, {
    "volume" : 1571019,
    "marketCap" : 1336632638250,
    "lowPrice" : 6040,
    "highPrice" : 6370,
    "openPrice" : 6070,
    "tradeDate" : "2025-07-07",
    "closePrice" : 6230
  }, {
    "volume" : 2499602,
    "marketCap" : 1409578881750,
    "lowPrice" : 6130,
    "highPrice" : 6620,
    "openPrice" : 6150,
    "tradeDate" : "2025-07-08",
    "closePrice" : 6570
  }, {
    "volume" : 5689420,
    "marketCap" : 1497543469500,
    "lowPrice" : 6530,
    "highPrice" : 6990,
    "openPrice" : 6720,
    "tradeDate" : "2025-07-09",
    "closePrice" : 6980
  }, {
    "volume" : 4882036,
    "marketCap" : 1516852769250,
    "lowPrice" : 6940,
    "highPrice" : 7230,
    "openPrice" : 7190,
    "tradeDate" : "2025-07-10",
    "closePrice" : 7070
  }, {
    "volume" : 6027831,
    "marketCap" : 1557616846500,
    "lowPrice" : 7090,
    "highPrice" : 7490,
    "openPrice" : 7340,
    "tradeDate" : "2025-07-11",
    "closePrice" : 7260
  }, {
    "volume" : 3836811,
    "marketCap" : 1540453024500,
    "lowPrice" : 6880,
    "highPrice" : 7270,
    "openPrice" : 7260,
    "tradeDate" : "2025-07-14",
    "closePrice" : 7180
  }, {
    "volume" : 2432196,
    "marketCap" : 1501834425000,
    "lowPrice" : 6920,
    "highPrice" : 7160,
    "openPrice" : 7110,
    "tradeDate" : "2025-07-15",
    "closePrice" : 7000
  }, {
    "volume" : 3048180,
    "marketCap" : 1420306270500,
    "lowPrice" : 6570,
    "highPrice" : 6870,
    "openPrice" : 6840,
    "tradeDate" : "2025-07-16",
    "closePrice" : 6620
  }, {
    "volume" : 1815532,
    "marketCap" : 1411724359500,
    "lowPrice" : 6500,
    "highPrice" : 6750,
    "openPrice" : 6720,
    "tradeDate" : "2025-07-17",
    "closePrice" : 6580
  }, {
    "volume" : 1458539,
    "marketCap" : 1411724359500,
    "lowPrice" : 6470,
    "highPrice" : 6670,
    "openPrice" : 6650,
    "tradeDate" : "2025-07-18",
    "closePrice" : 6580
  }, {
    "volume" : 1802370,
    "marketCap" : 1383833148750,
    "lowPrice" : 6400,
    "highPrice" : 6600,
    "openPrice" : 6470,
    "tradeDate" : "2025-07-21",
    "closePrice" : 6450
  }, {
    "volume" : 1338217,
    "marketCap" : 1368814804500,
    "lowPrice" : 6310,
    "highPrice" : 6570,
    "openPrice" : 6500,
    "tradeDate" : "2025-07-22",
    "closePrice" : 6380
  }, {
    "volume" : 1199102,
    "marketCap" : 1336632638250,
    "lowPrice" : 6180,
    "highPrice" : 6410,
    "openPrice" : 6410,
    "tradeDate" : "2025-07-23",
    "closePrice" : 6230
  }, {
    "volume" : 1478015,
    "marketCap" : 1321614294000,
    "lowPrice" : 6050,
    "highPrice" : 6330,
    "openPrice" : 6260,
    "tradeDate" : "2025-07-24",
    "closePrice" : 6160
  }, {
    "volume" : 1166262,
    "marketCap" : 1325905249500,
    "lowPrice" : 6100,
    "highPrice" : 6390,
    "openPrice" : 6110,
    "tradeDate" : "2025-07-25",
    "closePrice" : 6180
  }, {
    "volume" : 1471681,
    "marketCap" : 1291577605500,
    "lowPrice" : 5980,
    "highPrice" : 6230,
    "openPrice" : 6220,
    "tradeDate" : "2025-07-28",
    "closePrice" : 6020
  }, {
    "volume" : 1146635,
    "marketCap" : 1274413783500,
    "lowPrice" : 5860,
    "highPrice" : 6020,
    "openPrice" : 6000,
    "tradeDate" : "2025-07-29",
    "closePrice" : 5940
  }, {
    "volume" : 1498595,
    "marketCap" : 1242231617250,
    "lowPrice" : 5770,
    "highPrice" : 6010,
    "openPrice" : 6000,
    "tradeDate" : "2025-07-30",
    "closePrice" : 5790
  }, {
    "volume" : 1105280,
    "marketCap" : 1257249961500,
    "lowPrice" : 5770,
    "highPrice" : 5970,
    "openPrice" : 5830,
    "tradeDate" : "2025-07-31",
    "closePrice" : 5860
  }, {
    "volume" : 2405231,
    "marketCap" : 1164994418250,
    "lowPrice" : 5410,
    "highPrice" : 5730,
    "openPrice" : 5730,
    "tradeDate" : "2025-08-01",
    "closePrice" : 5430
  }, {
    "volume" : 1179615,
    "marketCap" : 1201467540000,
    "lowPrice" : 5410,
    "highPrice" : 5610,
    "openPrice" : 5420,
    "tradeDate" : "2025-08-04",
    "closePrice" : 5600
  }, {
    "volume" : 1176823,
    "marketCap" : 1210049451000,
    "lowPrice" : 5570,
    "highPrice" : 5750,
    "openPrice" : 5620,
    "tradeDate" : "2025-08-05",
    "closePrice" : 5640
  }, {
    "volume" : 625746,
    "marketCap" : 1218631362000,
    "lowPrice" : 5520,
    "highPrice" : 5710,
    "openPrice" : 5590,
    "tradeDate" : "2025-08-06",
    "closePrice" : 5680
  }, {
    "volume" : 1112591,
    "marketCap" : 1222922317500,
    "lowPrice" : 5640,
    "highPrice" : 5810,
    "openPrice" : 5800,
    "tradeDate" : "2025-08-07",
    "closePrice" : 5700
  }, {
    "volume" : 654087,
    "marketCap" : 1203613017750,
    "lowPrice" : 5610,
    "highPrice" : 5760,
    "openPrice" : 5710,
    "tradeDate" : "2025-08-08",
    "closePrice" : 5610
  }, {
    "volume" : 1701263,
    "marketCap" : 1212194928750,
    "lowPrice" : 5390,
    "highPrice" : 5760,
    "openPrice" : 5680,
    "tradeDate" : "2025-08-11",
    "closePrice" : 5650
  }, {
    "volume" : 1311317,
    "marketCap" : 1205758495500,
    "lowPrice" : 5600,
    "highPrice" : 5890,
    "openPrice" : 5640,
    "tradeDate" : "2025-08-12",
    "closePrice" : 5620
  }, {
    "volume" : 495896,
    "marketCap" : 1210049451000,
    "lowPrice" : 5550,
    "highPrice" : 5720,
    "openPrice" : 5720,
    "tradeDate" : "2025-08-13",
    "closePrice" : 5640
  }, {
    "volume" : 860048,
    "marketCap" : 1212194928750,
    "lowPrice" : 5600,
    "highPrice" : 5860,
    "openPrice" : 5750,
    "tradeDate" : "2025-08-14",
    "closePrice" : 5650
  }, {
    "volume" : 1093906,
    "marketCap" : 1164994418250,
    "lowPrice" : 5370,
    "highPrice" : 5580,
    "openPrice" : 5560,
    "tradeDate" : "2025-08-18",
    "closePrice" : 5430
  }, {
    "volume" : 895368,
    "marketCap" : 1160703462750,
    "lowPrice" : 5300,
    "highPrice" : 5500,
    "openPrice" : 5420,
    "tradeDate" : "2025-08-19",
    "closePrice" : 5410
  }, {
    "volume" : 2263270,
    "marketCap" : 1134957729750,
    "lowPrice" : 5060,
    "highPrice" : 5300,
    "openPrice" : 5260,
    "tradeDate" : "2025-08-20",
    "closePrice" : 5290
  }, {
    "volume" : 1501158,
    "marketCap" : 1162848940500,
    "lowPrice" : 5300,
    "highPrice" : 5520,
    "openPrice" : 5320,
    "tradeDate" : "2025-08-21",
    "closePrice" : 5420
  }, {
    "volume" : 834133,
    "marketCap" : 1162848940500,
    "lowPrice" : 5390,
    "highPrice" : 5520,
    "openPrice" : 5410,
    "tradeDate" : "2025-08-22",
    "closePrice" : 5420
  }, {
    "volume" : 3927844,
    "marketCap" : 1231504228500,
    "lowPrice" : 5490,
    "highPrice" : 5910,
    "openPrice" : 5490,
    "tradeDate" : "2025-08-25",
    "closePrice" : 5740
  }, {
    "volume" : 1243140,
    "marketCap" : 1197176584500,
    "lowPrice" : 5540,
    "highPrice" : 5750,
    "openPrice" : 5750,
    "tradeDate" : "2025-08-26",
    "closePrice" : 5580
  }, {
    "volume" : 1011935,
    "marketCap" : 1186449195750,
    "lowPrice" : 5440,
    "highPrice" : 5610,
    "openPrice" : 5610,
    "tradeDate" : "2025-08-27",
    "closePrice" : 5530
  }, {
    "volume" : 2316594,
    "marketCap" : 1207903973250,
    "lowPrice" : 5420,
    "highPrice" : 5740,
    "openPrice" : 5470,
    "tradeDate" : "2025-08-28",
    "closePrice" : 5630
  }, {
    "volume" : 958955,
    "marketCap" : 1188594673500,
    "lowPrice" : 5530,
    "highPrice" : 5710,
    "openPrice" : 5660,
    "tradeDate" : "2025-08-29",
    "closePrice" : 5540
  }, {
    "volume" : 986204,
    "marketCap" : 1154267029500,
    "lowPrice" : 5340,
    "highPrice" : 5570,
    "openPrice" : 5520,
    "tradeDate" : "2025-09-01",
    "closePrice" : 5380
  }, {
    "volume" : 741768,
    "marketCap" : 1154267029500,
    "lowPrice" : 5300,
    "highPrice" : 5420,
    "openPrice" : 5380,
    "tradeDate" : "2025-09-02",
    "closePrice" : 5380
  }, {
    "volume" : 576236,
    "marketCap" : 1158557985000,
    "lowPrice" : 5310,
    "highPrice" : 5400,
    "openPrice" : 5380,
    "tradeDate" : "2025-09-03",
    "closePrice" : 5400
  }, {
    "volume" : 743696,
    "marketCap" : 1167139896000,
    "lowPrice" : 5340,
    "highPrice" : 5480,
    "openPrice" : 5390,
    "tradeDate" : "2025-09-04",
    "closePrice" : 5440
  }, {
    "volume" : 1285455,
    "marketCap" : 1188594673500,
    "lowPrice" : 5350,
    "highPrice" : 5620,
    "openPrice" : 5460,
    "tradeDate" : "2025-09-05",
    "closePrice" : 5540
  }, {
    "volume" : 1763304,
    "marketCap" : 1227213273000,
    "lowPrice" : 5520,
    "highPrice" : 5850,
    "openPrice" : 5540,
    "tradeDate" : "2025-09-08",
    "closePrice" : 5720
  }, {
    "volume" : 5247998,
    "marketCap" : 1291577605500,
    "lowPrice" : 5760,
    "highPrice" : 6100,
    "openPrice" : 5820,
    "tradeDate" : "2025-09-09",
    "closePrice" : 6020
  }, {
    "volume" : 3647166,
    "marketCap" : 1321614294000,
    "lowPrice" : 5960,
    "highPrice" : 6210,
    "openPrice" : 6070,
    "tradeDate" : "2025-09-10",
    "closePrice" : 6160
  }, {
    "volume" : 2609655,
    "marketCap" : 1308741427500,
    "lowPrice" : 5910,
    "highPrice" : 6160,
    "openPrice" : 6150,
    "tradeDate" : "2025-09-11",
    "closePrice" : 6100
  }, {
    "volume" : 1518472,
    "marketCap" : 1310886905250,
    "lowPrice" : 6050,
    "highPrice" : 6230,
    "openPrice" : 6200,
    "tradeDate" : "2025-09-12",
    "closePrice" : 6110
  }, {
    "volume" : 3003801,
    "marketCap" : 1325905249500,
    "lowPrice" : 6130,
    "highPrice" : 6290,
    "openPrice" : 6150,
    "tradeDate" : "2025-09-15",
    "closePrice" : 6180
  }, {
    "volume" : 1874551,
    "marketCap" : 1315177860750,
    "lowPrice" : 6020,
    "highPrice" : 6220,
    "openPrice" : 6180,
    "tradeDate" : "2025-09-16",
    "closePrice" : 6130
  }, {
    "volume" : 912710,
    "marketCap" : 1308741427500,
    "lowPrice" : 6000,
    "highPrice" : 6120,
    "openPrice" : 6110,
    "tradeDate" : "2025-09-17",
    "closePrice" : 6100
  }, {
    "volume" : 1335494,
    "marketCap" : 1321614294000,
    "lowPrice" : 6020,
    "highPrice" : 6170,
    "openPrice" : 6140,
    "tradeDate" : "2025-09-18",
    "closePrice" : 6160
  }, {
    "volume" : 935766,
    "marketCap" : 1308741427500,
    "lowPrice" : 6030,
    "highPrice" : 6210,
    "openPrice" : 6160,
    "tradeDate" : "2025-09-19",
    "closePrice" : 6100
  }, {
    "volume" : 1243664,
    "marketCap" : 1276559261250,
    "lowPrice" : 5910,
    "highPrice" : 6090,
    "openPrice" : 6090,
    "tradeDate" : "2025-09-22",
    "closePrice" : 5950
  }, {
    "volume" : 1424090,
    "marketCap" : 1248668050500,
    "lowPrice" : 5770,
    "highPrice" : 6030,
    "openPrice" : 5970,
    "tradeDate" : "2025-09-23",
    "closePrice" : 5820
  }, {
    "volume" : 1442581,
    "marketCap" : 1218631362000,
    "lowPrice" : 5580,
    "highPrice" : 5810,
    "openPrice" : 5800,
    "tradeDate" : "2025-09-24",
    "closePrice" : 5680
  }, {
    "volume" : 3443290,
    "marketCap" : 1158557985000,
    "lowPrice" : 5320,
    "highPrice" : 5730,
    "openPrice" : 5650,
    "tradeDate" : "2025-09-25",
    "closePrice" : 5400
  }, {
    "volume" : 2066248,
    "marketCap" : 1134957729750,
    "lowPrice" : 5220,
    "highPrice" : 5480,
    "openPrice" : 5450,
    "tradeDate" : "2025-09-26",
    "closePrice" : 5290
  }, {
    "volume" : 17613503,
    "marketCap" : 1330196205000,
    "lowPrice" : 5440,
    "highPrice" : 6300,
    "openPrice" : 5440,
    "tradeDate" : "2025-09-29",
    "closePrice" : 6200
  }, {
    "volume" : 23566589,
    "marketCap" : 1366669326750,
    "lowPrice" : 5940,
    "highPrice" : 6690,
    "openPrice" : 6410,
    "tradeDate" : "2025-09-30",
    "closePrice" : 6370
  }, {
    "volume" : 7484094,
    "marketCap" : 1244377095000,
    "lowPrice" : 5780,
    "highPrice" : 6370,
    "openPrice" : 6370,
    "tradeDate" : "2025-10-01",
    "closePrice" : 5800
  }, {
    "volume" : 8418423,
    "marketCap" : 1267977350250,
    "lowPrice" : 5750,
    "highPrice" : 6140,
    "openPrice" : 5910,
    "tradeDate" : "2025-10-02",
    "closePrice" : 5910
  }, {
    "volume" : 5852503,
    "marketCap" : 1287286650000,
    "lowPrice" : 5910,
    "highPrice" : 6240,
    "openPrice" : 5950,
    "tradeDate" : "2025-10-10",
    "closePrice" : 6000
  }, {
    "volume" : 3222779,
    "marketCap" : 1222922317500,
    "lowPrice" : 5630,
    "highPrice" : 5970,
    "openPrice" : 5830,
    "tradeDate" : "2025-10-13",
    "closePrice" : 5700
  }, {
    "volume" : 2372551,
    "marketCap" : 1180012762500,
    "lowPrice" : 5420,
    "highPrice" : 5790,
    "openPrice" : 5720,
    "tradeDate" : "2025-10-14",
    "closePrice" : 5500
  }, {
    "volume" : 2047786,
    "marketCap" : 1235795184000,
    "lowPrice" : 5470,
    "highPrice" : 5760,
    "openPrice" : 5500,
    "tradeDate" : "2025-10-15",
    "closePrice" : 5760
  }, {
    "volume" : 2162017,
    "marketCap" : 1244377095000,
    "lowPrice" : 5710,
    "highPrice" : 5970,
    "openPrice" : 5760,
    "tradeDate" : "2025-10-16",
    "closePrice" : 5800
  }, {
    "volume" : 5926886,
    "marketCap" : 1158557985000,
    "lowPrice" : 5240,
    "highPrice" : 5750,
    "openPrice" : 5750,
    "tradeDate" : "2025-10-17",
    "closePrice" : 5400
  }, {
    "volume" : 7631501,
    "marketCap" : 1210049451000,
    "lowPrice" : 5220,
    "highPrice" : 5660,
    "openPrice" : 5420,
    "tradeDate" : "2025-10-20",
    "closePrice" : 5640
  }, {
    "volume" : 8207244,
    "marketCap" : 1134957729750,
    "lowPrice" : 5200,
    "highPrice" : 5720,
    "openPrice" : 5710,
    "tradeDate" : "2025-10-21",
    "closePrice" : 5290
  }, {
    "volume" : 2604457,
    "marketCap" : 1147830596250,
    "lowPrice" : 5160,
    "highPrice" : 5350,
    "openPrice" : 5320,
    "tradeDate" : "2025-10-22",
    "closePrice" : 5350
  }, {
    "volume" : 2070034,
    "marketCap" : 1119939385500,
    "lowPrice" : 5190,
    "highPrice" : 5330,
    "openPrice" : 5240,
    "tradeDate" : "2025-10-23",
    "closePrice" : 5220
  }, {
    "volume" : 2542007,
    "marketCap" : 1152121551750,
    "lowPrice" : 5240,
    "highPrice" : 5400,
    "openPrice" : 5320,
    "tradeDate" : "2025-10-24",
    "closePrice" : 5370
  }, {
    "volume" : 4676805,
    "marketCap" : 1199322062250,
    "lowPrice" : 5450,
    "highPrice" : 5690,
    "openPrice" : 5460,
    "tradeDate" : "2025-10-27",
    "closePrice" : 5590
  }, {
    "volume" : 1980742,
    "marketCap" : 1175721807000,
    "lowPrice" : 5420,
    "highPrice" : 5580,
    "openPrice" : 5540,
    "tradeDate" : "2025-10-28",
    "closePrice" : 5480
  }, {
    "volume" : 2235866,
    "marketCap" : 1175721807000,
    "lowPrice" : 5410,
    "highPrice" : 5570,
    "openPrice" : 5510,
    "tradeDate" : "2025-10-29",
    "closePrice" : 5480
  }, {
    "volume" : 2357143,
    "marketCap" : 1154267029500,
    "lowPrice" : 5340,
    "highPrice" : 5630,
    "openPrice" : 5550,
    "tradeDate" : "2025-10-30",
    "closePrice" : 5380
  }, {
    "volume" : 1457932,
    "marketCap" : 1147830596250,
    "lowPrice" : 5300,
    "highPrice" : 5460,
    "openPrice" : 5380,
    "tradeDate" : "2025-10-31",
    "closePrice" : 5350
  }, {
    "volume" : 2308945,
    "marketCap" : 1145685118500,
    "lowPrice" : 5290,
    "highPrice" : 5520,
    "openPrice" : 5400,
    "tradeDate" : "2025-11-03",
    "closePrice" : 5340
  }, {
    "volume" : 1918036,
    "marketCap" : 1122084863250,
    "lowPrice" : 5220,
    "highPrice" : 5330,
    "openPrice" : 5290,
    "tradeDate" : "2025-11-04",
    "closePrice" : 5230
  }, {
    "volume" : 3046889,
    "marketCap" : 1087757219250,
    "lowPrice" : 4855,
    "highPrice" : 5190,
    "openPrice" : 5150,
    "tradeDate" : "2025-11-05",
    "closePrice" : 5070
  }, {
    "volume" : 2148899,
    "marketCap" : 1119939385500,
    "lowPrice" : 5030,
    "highPrice" : 5300,
    "openPrice" : 5150,
    "tradeDate" : "2025-11-06",
    "closePrice" : 5220
  }, {
    "volume" : 2036610,
    "marketCap" : 1077029830500,
    "lowPrice" : 4910,
    "highPrice" : 5190,
    "openPrice" : 5050,
    "tradeDate" : "2025-11-07",
    "closePrice" : 5020
  }, {
    "volume" : 2462604,
    "marketCap" : 1141394163000,
    "lowPrice" : 5090,
    "highPrice" : 5320,
    "openPrice" : 5090,
    "tradeDate" : "2025-11-10",
    "closePrice" : 5320
  }, {
    "volume" : 1742205,
    "marketCap" : 1109211996750,
    "lowPrice" : 5110,
    "highPrice" : 5460,
    "openPrice" : 5320,
    "tradeDate" : "2025-11-11",
    "closePrice" : 5170
  }, {
    "volume" : 1861067,
    "marketCap" : 1147830596250,
    "lowPrice" : 5150,
    "highPrice" : 5370,
    "openPrice" : 5210,
    "tradeDate" : "2025-11-12",
    "closePrice" : 5350
  }, {
    "volume" : 1586646,
    "marketCap" : 1160703462750,
    "lowPrice" : 5310,
    "highPrice" : 5440,
    "openPrice" : 5380,
    "tradeDate" : "2025-11-13",
    "closePrice" : 5410
  }, {
    "volume" : 1902304,
    "marketCap" : 1109211996750,
    "lowPrice" : 5150,
    "highPrice" : 5400,
    "openPrice" : 5330,
    "tradeDate" : "2025-11-14",
    "closePrice" : 5170
  }, {
    "volume" : 1303495,
    "marketCap" : 1092048174750,
    "lowPrice" : 5050,
    "highPrice" : 5190,
    "openPrice" : 5190,
    "tradeDate" : "2025-11-17",
    "closePrice" : 5090
  }, {
    "volume" : 2512436,
    "marketCap" : 1026611103375,
    "lowPrice" : 4780,
    "highPrice" : 5020,
    "openPrice" : 5000,
    "tradeDate" : "2025-11-18",
    "closePrice" : 4785
  }, {
    "volume" : 1152125,
    "marketCap" : 1036265753250,
    "lowPrice" : 4705,
    "highPrice" : 4900,
    "openPrice" : 4805,
    "tradeDate" : "2025-11-19",
    "closePrice" : 4830
  }, {
    "volume" : 3106454,
    "marketCap" : 1109211996750,
    "lowPrice" : 5070,
    "highPrice" : 5300,
    "openPrice" : 5100,
    "tradeDate" : "2025-11-20",
    "closePrice" : 5170
  }, {
    "volume" : 1534473,
    "marketCap" : 1074884352750,
    "lowPrice" : 4955,
    "highPrice" : 5110,
    "openPrice" : 4970,
    "tradeDate" : "2025-11-21",
    "closePrice" : 5010
  }, {
    "volume" : 1481123,
    "marketCap" : 1070593397250,
    "lowPrice" : 4955,
    "highPrice" : 5180,
    "openPrice" : 5180,
    "tradeDate" : "2025-11-24",
    "closePrice" : 4990
  }, {
    "volume" : 1706989,
    "marketCap" : 1059866008500,
    "lowPrice" : 4890,
    "highPrice" : 5170,
    "openPrice" : 5070,
    "tradeDate" : "2025-11-25",
    "closePrice" : 4940
  }, {
    "volume" : 1907074,
    "marketCap" : 1083466263750,
    "lowPrice" : 4950,
    "highPrice" : 5130,
    "openPrice" : 4990,
    "tradeDate" : "2025-11-26",
    "closePrice" : 5050
  }, {
    "volume" : 2524981,
    "marketCap" : 1059866008500,
    "lowPrice" : 4925,
    "highPrice" : 5190,
    "openPrice" : 5100,
    "tradeDate" : "2025-11-27",
    "closePrice" : 4940
  }, {
    "volume" : 1491628,
    "marketCap" : 1051284097500,
    "lowPrice" : 4840,
    "highPrice" : 4985,
    "openPrice" : 4940,
    "tradeDate" : "2025-11-28",
    "closePrice" : 4900
  }, {
    "volume" : 2104926,
    "marketCap" : 1016956453500,
    "lowPrice" : 4715,
    "highPrice" : 4960,
    "openPrice" : 4905,
    "tradeDate" : "2025-12-01",
    "closePrice" : 4740
  }, {
    "volume" : 1023818,
    "marketCap" : 1033047536625,
    "lowPrice" : 4710,
    "highPrice" : 4820,
    "openPrice" : 4740,
    "tradeDate" : "2025-12-02",
    "closePrice" : 4815
  }, {
    "volume" : 1409878,
    "marketCap" : 1051284097500,
    "lowPrice" : 4820,
    "highPrice" : 4940,
    "openPrice" : 4840,
    "tradeDate" : "2025-12-03",
    "closePrice" : 4900
  }, {
    "volume" : 1213181,
    "marketCap" : 1026611103375,
    "lowPrice" : 4760,
    "highPrice" : 4915,
    "openPrice" : 4915,
    "tradeDate" : "2025-12-04",
    "closePrice" : 4785
  }, {
    "volume" : 737607,
    "marketCap" : 1035193014375,
    "lowPrice" : 4760,
    "highPrice" : 4825,
    "openPrice" : 4775,
    "tradeDate" : "2025-12-05",
    "closePrice" : 4825
  }, {
    "volume" : 1263760,
    "marketCap" : 1014810975750,
    "lowPrice" : 4715,
    "highPrice" : 4865,
    "openPrice" : 4825,
    "tradeDate" : "2025-12-08",
    "closePrice" : 4730
  }, {
    "volume" : 1594008,
    "marketCap" : 1006229064750,
    "lowPrice" : 4635,
    "highPrice" : 4745,
    "openPrice" : 4725,
    "tradeDate" : "2025-12-09",
    "closePrice" : 4690
  }, {
    "volume" : 1116782,
    "marketCap" : 999792631500,
    "lowPrice" : 4650,
    "highPrice" : 4735,
    "openPrice" : 4720,
    "tradeDate" : "2025-12-10",
    "closePrice" : 4660
  }, {
    "volume" : 1266859,
    "marketCap" : 994428937125,
    "lowPrice" : 4635,
    "highPrice" : 4765,
    "openPrice" : 4700,
    "tradeDate" : "2025-12-11",
    "closePrice" : 4635
  }, {
    "volume" : 1347892,
    "marketCap" : 1027683842250,
    "lowPrice" : 4645,
    "highPrice" : 4795,
    "openPrice" : 4655,
    "tradeDate" : "2025-12-12",
    "closePrice" : 4790
  }, {
    "volume" : 855756,
    "marketCap" : 1009447281375,
    "lowPrice" : 4670,
    "highPrice" : 4780,
    "openPrice" : 4740,
    "tradeDate" : "2025-12-15",
    "closePrice" : 4705
  }, {
    "volume" : 1228432,
    "marketCap" : 985847026125,
    "lowPrice" : 4590,
    "highPrice" : 4710,
    "openPrice" : 4705,
    "tradeDate" : "2025-12-16",
    "closePrice" : 4595
  }, {
    "volume" : 790110,
    "marketCap" : 992283459375,
    "lowPrice" : 4585,
    "highPrice" : 4660,
    "openPrice" : 4620,
    "tradeDate" : "2025-12-17",
    "closePrice" : 4625
  }, {
    "volume" : 1003773,
    "marketCap" : 978337854000,
    "lowPrice" : 4500,
    "highPrice" : 4645,
    "openPrice" : 4580,
    "tradeDate" : "2025-12-18",
    "closePrice" : 4560
  }, {
    "volume" : 1571816,
    "marketCap" : 1006229064750,
    "lowPrice" : 4560,
    "highPrice" : 4755,
    "openPrice" : 4560,
    "tradeDate" : "2025-12-19",
    "closePrice" : 4690
  }, {
    "volume" : 2319604,
    "marketCap" : 1051284097500,
    "lowPrice" : 4710,
    "highPrice" : 4930,
    "openPrice" : 4730,
    "tradeDate" : "2025-12-22",
    "closePrice" : 4900
  } ],
  "stockCode" : "003530"
}