{
  "lastUpdated" : "2025-12-24",
  "stockName" : "현대홈쇼핑",
  "prices" : [ {
    "volume" : 17556,
    "marketCap" : 557400000000,
    "lowPrice" : 45800,
    "highPrice" : 47000,
    "openPrice" : 46200,
    "tradeDate" : "2024-12-24",
    "closePrice" : 46450
  }, {
    "volume" : 23257,
    "marketCap" : 570000000000,
    "lowPrice" : 45500,
    "highPrice" : 47500,
    "openPrice" : 46600,
    "tradeDate" : "2024-12-26",
    "closePrice" : 47500
  }, {
    "volume" : 24794,
    "marketCap" : 547800000000,
    "lowPrice" : 44650,
    "highPrice" : 46400,
    "openPrice" : 46400,
    "tradeDate" : "2024-12-27",
    "closePrice" : 45650
  }, {
    "volume" : 12597,
    "marketCap" : 544800000000,
    "lowPrice" : 44650,
    "highPrice" : 46150,
    "openPrice" : 45000,
    "tradeDate" : "2024-12-30",
    "closePrice" : 45400
  }, {
    "volume" : 8002,
    "marketCap" : 537600000000,
    "lowPrice" : 44750,
    "highPrice" : 45300,
    "openPrice" : 45100,
    "tradeDate" : "2025-01-02",
    "closePrice" : 44800
  }, {
    "volume" : 7648,
    "marketCap" : 535800000000,
    "lowPrice" : 44650,
    "highPrice" : 45150,
    "openPrice" : 44800,
    "tradeDate" : "2025-01-03",
    "closePrice" : 44650
  }, {
    "volume" : 9863,
    "marketCap" : 534000000000,
    "lowPrice" : 44450,
    "highPrice" : 45000,
    "openPrice" : 44700,
    "tradeDate" : "2025-01-06",
    "closePrice" : 44500
  }, {
    "volume" : 7295,
    "marketCap" : 535200000000,
    "lowPrice" : 44350,
    "highPrice" : 44850,
    "openPrice" : 44500,
    "tradeDate" : "2025-01-07",
    "closePrice" : 44600
  }, {
    "volume" : 6232,
    "marketCap" : 535200000000,
    "lowPrice" : 44200,
    "highPrice" : 44900,
    "openPrice" : 44550,
    "tradeDate" : "2025-01-08",
    "closePrice" : 44600
  }, {
    "volume" : 9828,
    "marketCap" : 531600000000,
    "lowPrice" : 44100,
    "highPrice" : 44700,
    "openPrice" : 44600,
    "tradeDate" : "2025-01-09",
    "closePrice" : 44300
  }, {
    "volume" : 21102,
    "marketCap" : 522000000000,
    "lowPrice" : 43500,
    "highPrice" : 44900,
    "openPrice" : 44300,
    "tradeDate" : "2025-01-10",
    "closePrice" : 43500
  }, {
    "volume" : 8503,
    "marketCap" : 522000000000,
    "lowPrice" : 43350,
    "highPrice" : 43950,
    "openPrice" : 43550,
    "tradeDate" : "2025-01-13",
    "closePrice" : 43500
  }, {
    "volume" : 9921,
    "marketCap" : 529200000000,
    "lowPrice" : 43600,
    "highPrice" : 44300,
    "openPrice" : 43600,
    "tradeDate" : "2025-01-14",
    "closePrice" : 44100
  }, {
    "volume" : 5628,
    "marketCap" : 527400000000,
    "lowPrice" : 43900,
    "highPrice" : 44450,
    "openPrice" : 44100,
    "tradeDate" : "2025-01-15",
    "closePrice" : 43950
  }, {
    "volume" : 5568,
    "marketCap" : 528000000000,
    "lowPrice" : 43900,
    "highPrice" : 44400,
    "openPrice" : 44000,
    "tradeDate" : "2025-01-16",
    "closePrice" : 44000
  }, {
    "volume" : 9520,
    "marketCap" : 523800000000,
    "lowPrice" : 43500,
    "highPrice" : 44200,
    "openPrice" : 44050,
    "tradeDate" : "2025-01-17",
    "closePrice" : 43650
  }, {
    "volume" : 5706,
    "marketCap" : 528000000000,
    "lowPrice" : 43650,
    "highPrice" : 44200,
    "openPrice" : 43750,
    "tradeDate" : "2025-01-20",
    "closePrice" : 44000
  }, {
    "volume" : 5789,
    "marketCap" : 528600000000,
    "lowPrice" : 43850,
    "highPrice" : 44350,
    "openPrice" : 44050,
    "tradeDate" : "2025-01-21",
    "closePrice" : 44050
  }, {
    "volume" : 7217,
    "marketCap" : 526200000000,
    "lowPrice" : 43650,
    "highPrice" : 44150,
    "openPrice" : 43850,
    "tradeDate" : "2025-01-22",
    "closePrice" : 43850
  }, {
    "volume" : 8934,
    "marketCap" : 526200000000,
    "lowPrice" : 43650,
    "highPrice" : 44150,
    "openPrice" : 43850,
    "tradeDate" : "2025-01-23",
    "closePrice" : 43850
  }, {
    "volume" : 54670,
    "marketCap" : 561600000000,
    "lowPrice" : 43950,
    "highPrice" : 47700,
    "openPrice" : 44050,
    "tradeDate" : "2025-01-24",
    "closePrice" : 46800
  }, {
    "volume" : 50397,
    "marketCap" : 580800000000,
    "lowPrice" : 46550,
    "highPrice" : 48400,
    "openPrice" : 46900,
    "tradeDate" : "2025-01-31",
    "closePrice" : 48400
  }, {
    "volume" : 39957,
    "marketCap" : 586800000000,
    "lowPrice" : 47650,
    "highPrice" : 48950,
    "openPrice" : 48150,
    "tradeDate" : "2025-02-03",
    "closePrice" : 48900
  }, {
    "volume" : 32638,
    "marketCap" : 597000000000,
    "lowPrice" : 48800,
    "highPrice" : 50200,
    "openPrice" : 49000,
    "tradeDate" : "2025-02-04",
    "closePrice" : 49750
  }, {
    "volume" : 58891,
    "marketCap" : 630000000000,
    "lowPrice" : 50000,
    "highPrice" : 52900,
    "openPrice" : 50000,
    "tradeDate" : "2025-02-05",
    "closePrice" : 52500
  }, {
    "volume" : 38700,
    "marketCap" : 615600000000,
    "lowPrice" : 50000,
    "highPrice" : 53600,
    "openPrice" : 52500,
    "tradeDate" : "2025-02-06",
    "closePrice" : 51300
  }, {
    "volume" : 20756,
    "marketCap" : 612000000000,
    "lowPrice" : 50700,
    "highPrice" : 52000,
    "openPrice" : 51400,
    "tradeDate" : "2025-02-07",
    "closePrice" : 51000
  }, {
    "volume" : 36673,
    "marketCap" : 600000000000,
    "lowPrice" : 49950,
    "highPrice" : 51600,
    "openPrice" : 50900,
    "tradeDate" : "2025-02-10",
    "closePrice" : 50000
  }, {
    "volume" : 23304,
    "marketCap" : 597600000000,
    "lowPrice" : 49300,
    "highPrice" : 50800,
    "openPrice" : 50200,
    "tradeDate" : "2025-02-11",
    "closePrice" : 49800
  }, {
    "volume" : 43564,
    "marketCap" : 589800000000,
    "lowPrice" : 48700,
    "highPrice" : 49900,
    "openPrice" : 49900,
    "tradeDate" : "2025-02-12",
    "closePrice" : 49150
  }, {
    "volume" : 30419,
    "marketCap" : 587400000000,
    "lowPrice" : 48400,
    "highPrice" : 49100,
    "openPrice" : 48700,
    "tradeDate" : "2025-02-13",
    "closePrice" : 48950
  }, {
    "volume" : 18420,
    "marketCap" : 590400000000,
    "lowPrice" : 48750,
    "highPrice" : 49650,
    "openPrice" : 48800,
    "tradeDate" : "2025-02-14",
    "closePrice" : 49200
  }, {
    "volume" : 39461,
    "marketCap" : 586200000000,
    "lowPrice" : 48500,
    "highPrice" : 49250,
    "openPrice" : 49200,
    "tradeDate" : "2025-02-17",
    "closePrice" : 48850
  }, {
    "volume" : 14559,
    "marketCap" : 588600000000,
    "lowPrice" : 48850,
    "highPrice" : 49450,
    "openPrice" : 48900,
    "tradeDate" : "2025-02-18",
    "closePrice" : 49050
  }, {
    "volume" : 23274,
    "marketCap" : 589200000000,
    "lowPrice" : 49000,
    "highPrice" : 49250,
    "openPrice" : 49250,
    "tradeDate" : "2025-02-19",
    "closePrice" : 49100
  }, {
    "volume" : 76875,
    "marketCap" : 619200000000,
    "lowPrice" : 49050,
    "highPrice" : 52400,
    "openPrice" : 49150,
    "tradeDate" : "2025-02-20",
    "closePrice" : 51600
  }, {
    "volume" : 18760,
    "marketCap" : 628800000000,
    "lowPrice" : 51100,
    "highPrice" : 52500,
    "openPrice" : 51600,
    "tradeDate" : "2025-02-21",
    "closePrice" : 52400
  }, {
    "volume" : 20734,
    "marketCap" : 621600000000,
    "lowPrice" : 51200,
    "highPrice" : 52300,
    "openPrice" : 52000,
    "tradeDate" : "2025-02-24",
    "closePrice" : 51800
  }, {
    "volume" : 12782,
    "marketCap" : 625200000000,
    "lowPrice" : 51200,
    "highPrice" : 52600,
    "openPrice" : 52600,
    "tradeDate" : "2025-02-25",
    "closePrice" : 52100
  }, {
    "volume" : 12248,
    "marketCap" : 612000000000,
    "lowPrice" : 50800,
    "highPrice" : 52000,
    "openPrice" : 51500,
    "tradeDate" : "2025-02-26",
    "closePrice" : 51000
  }, {
    "volume" : 23000,
    "marketCap" : 630000000000,
    "lowPrice" : 50900,
    "highPrice" : 52500,
    "openPrice" : 51000,
    "tradeDate" : "2025-02-27",
    "closePrice" : 52500
  }, {
    "volume" : 19083,
    "marketCap" : 625200000000,
    "lowPrice" : 51300,
    "highPrice" : 52600,
    "openPrice" : 52000,
    "tradeDate" : "2025-02-28",
    "closePrice" : 52100
  }, {
    "volume" : 15381,
    "marketCap" : 613200000000,
    "lowPrice" : 51100,
    "highPrice" : 52400,
    "openPrice" : 51900,
    "tradeDate" : "2025-03-04",
    "closePrice" : 51100
  }, {
    "volume" : 11392,
    "marketCap" : 622800000000,
    "lowPrice" : 51100,
    "highPrice" : 52000,
    "openPrice" : 51100,
    "tradeDate" : "2025-03-05",
    "closePrice" : 51900
  }, {
    "volume" : 17807,
    "marketCap" : 609600000000,
    "lowPrice" : 50400,
    "highPrice" : 51800,
    "openPrice" : 51800,
    "tradeDate" : "2025-03-06",
    "closePrice" : 50800
  }, {
    "volume" : 12571,
    "marketCap" : 618000000000,
    "lowPrice" : 50500,
    "highPrice" : 51700,
    "openPrice" : 50800,
    "tradeDate" : "2025-03-07",
    "closePrice" : 51500
  }, {
    "volume" : 11926,
    "marketCap" : 608400000000,
    "lowPrice" : 50300,
    "highPrice" : 51600,
    "openPrice" : 51000,
    "tradeDate" : "2025-03-10",
    "closePrice" : 50700
  }, {
    "volume" : 12733,
    "marketCap" : 608400000000,
    "lowPrice" : 49500,
    "highPrice" : 50800,
    "openPrice" : 50600,
    "tradeDate" : "2025-03-11",
    "closePrice" : 50700
  }, {
    "volume" : 12452,
    "marketCap" : 603600000000,
    "lowPrice" : 50000,
    "highPrice" : 50700,
    "openPrice" : 50700,
    "tradeDate" : "2025-03-12",
    "closePrice" : 50300
  }, {
    "volume" : 14302,
    "marketCap" : 609600000000,
    "lowPrice" : 49850,
    "highPrice" : 51500,
    "openPrice" : 50300,
    "tradeDate" : "2025-03-13",
    "closePrice" : 50800
  }, {
    "volume" : 10975,
    "marketCap" : 613200000000,
    "lowPrice" : 50500,
    "highPrice" : 51300,
    "openPrice" : 50900,
    "tradeDate" : "2025-03-14",
    "closePrice" : 51100
  }, {
    "volume" : 14397,
    "marketCap" : 602400000000,
    "lowPrice" : 49950,
    "highPrice" : 51400,
    "openPrice" : 51100,
    "tradeDate" : "2025-03-17",
    "closePrice" : 50200
  }, {
    "volume" : 15904,
    "marketCap" : 601200000000,
    "lowPrice" : 49500,
    "highPrice" : 50400,
    "openPrice" : 50100,
    "tradeDate" : "2025-03-18",
    "closePrice" : 50100
  }, {
    "volume" : 10586,
    "marketCap" : 602400000000,
    "lowPrice" : 49850,
    "highPrice" : 50400,
    "openPrice" : 49900,
    "tradeDate" : "2025-03-19",
    "closePrice" : 50200
  }, {
    "volume" : 17906,
    "marketCap" : 606000000000,
    "lowPrice" : 49900,
    "highPrice" : 51000,
    "openPrice" : 50200,
    "tradeDate" : "2025-03-20",
    "closePrice" : 50500
  }, {
    "volume" : 46512,
    "marketCap" : 613200000000,
    "lowPrice" : 49600,
    "highPrice" : 52300,
    "openPrice" : 50300,
    "tradeDate" : "2025-03-21",
    "closePrice" : 51100
  }, {
    "volume" : 12698,
    "marketCap" : 601200000000,
    "lowPrice" : 49900,
    "highPrice" : 51700,
    "openPrice" : 51200,
    "tradeDate" : "2025-03-24",
    "closePrice" : 50100
  }, {
    "volume" : 10258,
    "marketCap" : 595800000000,
    "lowPrice" : 49350,
    "highPrice" : 50500,
    "openPrice" : 50100,
    "tradeDate" : "2025-03-25",
    "closePrice" : 49650
  }, {
    "volume" : 7414,
    "marketCap" : 590400000000,
    "lowPrice" : 49150,
    "highPrice" : 49700,
    "openPrice" : 49650,
    "tradeDate" : "2025-03-26",
    "closePrice" : 49200
  }, {
    "volume" : 4482,
    "marketCap" : 594600000000,
    "lowPrice" : 49000,
    "highPrice" : 49750,
    "openPrice" : 49200,
    "tradeDate" : "2025-03-27",
    "closePrice" : 49550
  }, {
    "volume" : 8359,
    "marketCap" : 589800000000,
    "lowPrice" : 48900,
    "highPrice" : 49600,
    "openPrice" : 49550,
    "tradeDate" : "2025-03-28",
    "closePrice" : 49150
  }, {
    "volume" : 12573,
    "marketCap" : 592800000000,
    "lowPrice" : 48500,
    "highPrice" : 49450,
    "openPrice" : 49300,
    "tradeDate" : "2025-03-31",
    "closePrice" : 49400
  }, {
    "volume" : 13023,
    "marketCap" : 599400000000,
    "lowPrice" : 49300,
    "highPrice" : 50000,
    "openPrice" : 49650,
    "tradeDate" : "2025-04-01",
    "closePrice" : 49950
  }, {
    "volume" : 14325,
    "marketCap" : 569400000000,
    "lowPrice" : 47200,
    "highPrice" : 48150,
    "openPrice" : 47800,
    "tradeDate" : "2025-04-02",
    "closePrice" : 47450
  }, {
    "volume" : 18330,
    "marketCap" : 564000000000,
    "lowPrice" : 46950,
    "highPrice" : 47850,
    "openPrice" : 47200,
    "tradeDate" : "2025-04-03",
    "closePrice" : 47000
  }, {
    "volume" : 12880,
    "marketCap" : 565200000000,
    "lowPrice" : 46300,
    "highPrice" : 47200,
    "openPrice" : 46800,
    "tradeDate" : "2025-04-04",
    "closePrice" : 47100
  }, {
    "volume" : 8920,
    "marketCap" : 543000000000,
    "lowPrice" : 45150,
    "highPrice" : 47000,
    "openPrice" : 47000,
    "tradeDate" : "2025-04-07",
    "closePrice" : 45250
  }, {
    "volume" : 14700,
    "marketCap" : 536400000000,
    "lowPrice" : 44650,
    "highPrice" : 45900,
    "openPrice" : 45500,
    "tradeDate" : "2025-04-08",
    "closePrice" : 44700
  }, {
    "volume" : 8773,
    "marketCap" : 536400000000,
    "lowPrice" : 44300,
    "highPrice" : 44900,
    "openPrice" : 44500,
    "tradeDate" : "2025-04-09",
    "closePrice" : 44700
  }, {
    "volume" : 9080,
    "marketCap" : 564000000000,
    "lowPrice" : 45000,
    "highPrice" : 47000,
    "openPrice" : 45000,
    "tradeDate" : "2025-04-10",
    "closePrice" : 47000
  }, {
    "volume" : 13976,
    "marketCap" : 579600000000,
    "lowPrice" : 46350,
    "highPrice" : 48300,
    "openPrice" : 46450,
    "tradeDate" : "2025-04-11",
    "closePrice" : 48300
  }, {
    "volume" : 6708,
    "marketCap" : 571200000000,
    "lowPrice" : 47500,
    "highPrice" : 48500,
    "openPrice" : 48100,
    "tradeDate" : "2025-04-14",
    "closePrice" : 47600
  }, {
    "volume" : 4990,
    "marketCap" : 577800000000,
    "lowPrice" : 47200,
    "highPrice" : 48200,
    "openPrice" : 47600,
    "tradeDate" : "2025-04-15",
    "closePrice" : 48150
  }, {
    "volume" : 1876,
    "marketCap" : 576000000000,
    "lowPrice" : 47600,
    "highPrice" : 48300,
    "openPrice" : 48150,
    "tradeDate" : "2025-04-16",
    "closePrice" : 48000
  }, {
    "volume" : 3204,
    "marketCap" : 575400000000,
    "lowPrice" : 47350,
    "highPrice" : 48450,
    "openPrice" : 48000,
    "tradeDate" : "2025-04-17",
    "closePrice" : 47950
  }, {
    "volume" : 11017,
    "marketCap" : 583200000000,
    "lowPrice" : 47700,
    "highPrice" : 49600,
    "openPrice" : 47700,
    "tradeDate" : "2025-04-18",
    "closePrice" : 48600
  }, {
    "volume" : 2863,
    "marketCap" : 581400000000,
    "lowPrice" : 48250,
    "highPrice" : 48950,
    "openPrice" : 48950,
    "tradeDate" : "2025-04-21",
    "closePrice" : 48450
  }, {
    "volume" : 4827,
    "marketCap" : 582000000000,
    "lowPrice" : 48050,
    "highPrice" : 48950,
    "openPrice" : 48250,
    "tradeDate" : "2025-04-22",
    "closePrice" : 48500
  }, {
    "volume" : 5309,
    "marketCap" : 579600000000,
    "lowPrice" : 47950,
    "highPrice" : 48750,
    "openPrice" : 48100,
    "tradeDate" : "2025-04-23",
    "closePrice" : 48300
  }, {
    "volume" : 7066,
    "marketCap" : 588600000000,
    "lowPrice" : 48050,
    "highPrice" : 49100,
    "openPrice" : 48300,
    "tradeDate" : "2025-04-24",
    "closePrice" : 49050
  }, {
    "volume" : 5775,
    "marketCap" : 589200000000,
    "lowPrice" : 48600,
    "highPrice" : 49350,
    "openPrice" : 49100,
    "tradeDate" : "2025-04-25",
    "closePrice" : 49100
  }, {
    "volume" : 6182,
    "marketCap" : 580200000000,
    "lowPrice" : 48250,
    "highPrice" : 49350,
    "openPrice" : 49300,
    "tradeDate" : "2025-04-28",
    "closePrice" : 48350
  }, {
    "volume" : 8407,
    "marketCap" : 586800000000,
    "lowPrice" : 48250,
    "highPrice" : 49300,
    "openPrice" : 48350,
    "tradeDate" : "2025-04-29",
    "closePrice" : 48900
  }, {
    "volume" : 9884,
    "marketCap" : 583200000000,
    "lowPrice" : 48550,
    "highPrice" : 49400,
    "openPrice" : 48550,
    "tradeDate" : "2025-04-30",
    "closePrice" : 48600
  }, {
    "volume" : 13882,
    "marketCap" : 585600000000,
    "lowPrice" : 48700,
    "highPrice" : 49800,
    "openPrice" : 49000,
    "tradeDate" : "2025-05-02",
    "closePrice" : 48800
  }, {
    "volume" : 9000,
    "marketCap" : 597000000000,
    "lowPrice" : 48600,
    "highPrice" : 49750,
    "openPrice" : 48600,
    "tradeDate" : "2025-05-07",
    "closePrice" : 49750
  }, {
    "volume" : 8749,
    "marketCap" : 594000000000,
    "lowPrice" : 48750,
    "highPrice" : 49550,
    "openPrice" : 49550,
    "tradeDate" : "2025-05-08",
    "closePrice" : 49500
  }, {
    "volume" : 7005,
    "marketCap" : 589200000000,
    "lowPrice" : 48400,
    "highPrice" : 49600,
    "openPrice" : 49500,
    "tradeDate" : "2025-05-09",
    "closePrice" : 49100
  }, {
    "volume" : 22444,
    "marketCap" : 610800000000,
    "lowPrice" : 48750,
    "highPrice" : 50900,
    "openPrice" : 48750,
    "tradeDate" : "2025-05-12",
    "closePrice" : 50900
  }, {
    "volume" : 12274,
    "marketCap" : 620400000000,
    "lowPrice" : 50400,
    "highPrice" : 51700,
    "openPrice" : 50400,
    "tradeDate" : "2025-05-13",
    "closePrice" : 51700
  }, {
    "volume" : 12004,
    "marketCap" : 620400000000,
    "lowPrice" : 51200,
    "highPrice" : 52100,
    "openPrice" : 51500,
    "tradeDate" : "2025-05-14",
    "closePrice" : 51700
  }, {
    "volume" : 4234,
    "marketCap" : 619200000000,
    "lowPrice" : 51000,
    "highPrice" : 52000,
    "openPrice" : 51700,
    "tradeDate" : "2025-05-15",
    "closePrice" : 51600
  }, {
    "volume" : 11384,
    "marketCap" : 610800000000,
    "lowPrice" : 49975,
    "highPrice" : 51500,
    "openPrice" : 51500,
    "tradeDate" : "2025-05-16",
    "closePrice" : 50900
  }, {
    "volume" : 5106,
    "marketCap" : 603600000000,
    "lowPrice" : 49600,
    "highPrice" : 51100,
    "openPrice" : 51000,
    "tradeDate" : "2025-05-19",
    "closePrice" : 50300
  }, {
    "volume" : 6596,
    "marketCap" : 615600000000,
    "lowPrice" : 49850,
    "highPrice" : 51300,
    "openPrice" : 50500,
    "tradeDate" : "2025-05-20",
    "closePrice" : 51300
  }, {
    "volume" : 6836,
    "marketCap" : 622800000000,
    "lowPrice" : 50900,
    "highPrice" : 51900,
    "openPrice" : 51100,
    "tradeDate" : "2025-05-21",
    "closePrice" : 51900
  }, {
    "volume" : 23793,
    "marketCap" : 638400000000,
    "lowPrice" : 51500,
    "highPrice" : 53600,
    "openPrice" : 51800,
    "tradeDate" : "2025-05-22",
    "closePrice" : 53200
  }, {
    "volume" : 31127,
    "marketCap" : 652800000000,
    "lowPrice" : 53000,
    "highPrice" : 54400,
    "openPrice" : 53300,
    "tradeDate" : "2025-05-23",
    "closePrice" : 54400
  }, {
    "volume" : 14361,
    "marketCap" : 651600000000,
    "lowPrice" : 53400,
    "highPrice" : 54600,
    "openPrice" : 54200,
    "tradeDate" : "2025-05-26",
    "closePrice" : 54300
  }, {
    "volume" : 20116,
    "marketCap" : 644400000000,
    "lowPrice" : 52600,
    "highPrice" : 54300,
    "openPrice" : 54300,
    "tradeDate" : "2025-05-27",
    "closePrice" : 53700
  }, {
    "volume" : 16093,
    "marketCap" : 648000000000,
    "lowPrice" : 53000,
    "highPrice" : 54200,
    "openPrice" : 53700,
    "tradeDate" : "2025-05-28",
    "closePrice" : 54000
  }, {
    "volume" : 27532,
    "marketCap" : 651600000000,
    "lowPrice" : 53100,
    "highPrice" : 54600,
    "openPrice" : 53700,
    "tradeDate" : "2025-05-29",
    "closePrice" : 54300
  }, {
    "volume" : 12129,
    "marketCap" : 655200000000,
    "lowPrice" : 53650,
    "highPrice" : 54800,
    "openPrice" : 54500,
    "tradeDate" : "2025-05-30",
    "closePrice" : 54600
  }, {
    "volume" : 34625,
    "marketCap" : 658800000000,
    "lowPrice" : 53500,
    "highPrice" : 55600,
    "openPrice" : 54900,
    "tradeDate" : "2025-06-02",
    "closePrice" : 54900
  }, {
    "volume" : 31718,
    "marketCap" : 676800000000,
    "lowPrice" : 54900,
    "highPrice" : 56700,
    "openPrice" : 55300,
    "tradeDate" : "2025-06-04",
    "closePrice" : 56400
  }, {
    "volume" : 17019,
    "marketCap" : 675600000000,
    "lowPrice" : 55500,
    "highPrice" : 56700,
    "openPrice" : 56300,
    "tradeDate" : "2025-06-05",
    "closePrice" : 56300
  }, {
    "volume" : 904863,
    "marketCap" : 696000000000,
    "lowPrice" : 56200,
    "highPrice" : 58300,
    "openPrice" : 56200,
    "tradeDate" : "2025-06-09",
    "closePrice" : 58000
  }, {
    "volume" : 21664,
    "marketCap" : 669600000000,
    "lowPrice" : 55000,
    "highPrice" : 58700,
    "openPrice" : 58600,
    "tradeDate" : "2025-06-10",
    "closePrice" : 55800
  }, {
    "volume" : 13611,
    "marketCap" : 681600000000,
    "lowPrice" : 55600,
    "highPrice" : 56800,
    "openPrice" : 55900,
    "tradeDate" : "2025-06-11",
    "closePrice" : 56800
  }, {
    "volume" : 24532,
    "marketCap" : 682800000000,
    "lowPrice" : 56100,
    "highPrice" : 57800,
    "openPrice" : 56800,
    "tradeDate" : "2025-06-12",
    "closePrice" : 56900
  }, {
    "volume" : 50585,
    "marketCap" : 656400000000,
    "lowPrice" : 53000,
    "highPrice" : 57300,
    "openPrice" : 57000,
    "tradeDate" : "2025-06-13",
    "closePrice" : 54700
  }, {
    "volume" : 23683,
    "marketCap" : 656400000000,
    "lowPrice" : 53200,
    "highPrice" : 54800,
    "openPrice" : 54600,
    "tradeDate" : "2025-06-16",
    "closePrice" : 54700
  }, {
    "volume" : 17856,
    "marketCap" : 642000000000,
    "lowPrice" : 53200,
    "highPrice" : 55000,
    "openPrice" : 54800,
    "tradeDate" : "2025-06-17",
    "closePrice" : 53500
  }, {
    "volume" : 27049,
    "marketCap" : 649200000000,
    "lowPrice" : 53100,
    "highPrice" : 55600,
    "openPrice" : 53700,
    "tradeDate" : "2025-06-18",
    "closePrice" : 54100
  }, {
    "volume" : 5744,
    "marketCap" : 652800000000,
    "lowPrice" : 53900,
    "highPrice" : 54700,
    "openPrice" : 54100,
    "tradeDate" : "2025-06-19",
    "closePrice" : 54400
  }, {
    "volume" : 18391,
    "marketCap" : 650400000000,
    "lowPrice" : 53400,
    "highPrice" : 55900,
    "openPrice" : 54600,
    "tradeDate" : "2025-06-20",
    "closePrice" : 54200
  }, {
    "volume" : 23433,
    "marketCap" : 661200000000,
    "lowPrice" : 54200,
    "highPrice" : 55500,
    "openPrice" : 54500,
    "tradeDate" : "2025-06-23",
    "closePrice" : 55100
  }, {
    "volume" : 12989,
    "marketCap" : 670800000000,
    "lowPrice" : 55000,
    "highPrice" : 56100,
    "openPrice" : 55400,
    "tradeDate" : "2025-06-24",
    "closePrice" : 55900
  }, {
    "volume" : 12230,
    "marketCap" : 676800000000,
    "lowPrice" : 55500,
    "highPrice" : 56500,
    "openPrice" : 56000,
    "tradeDate" : "2025-06-25",
    "closePrice" : 56400
  }, {
    "volume" : 12595,
    "marketCap" : 668400000000,
    "lowPrice" : 54500,
    "highPrice" : 56500,
    "openPrice" : 56500,
    "tradeDate" : "2025-06-26",
    "closePrice" : 55700
  }, {
    "volume" : 21265,
    "marketCap" : 676800000000,
    "lowPrice" : 54400,
    "highPrice" : 56700,
    "openPrice" : 55700,
    "tradeDate" : "2025-06-27",
    "closePrice" : 56400
  }, {
    "volume" : 20457,
    "marketCap" : 678000000000,
    "lowPrice" : 55300,
    "highPrice" : 57300,
    "openPrice" : 56900,
    "tradeDate" : "2025-06-30",
    "closePrice" : 56500
  }, {
    "volume" : 18291,
    "marketCap" : 684000000000,
    "lowPrice" : 55900,
    "highPrice" : 57500,
    "openPrice" : 55900,
    "tradeDate" : "2025-07-01",
    "closePrice" : 57000
  }, {
    "volume" : 19537,
    "marketCap" : 675600000000,
    "lowPrice" : 55300,
    "highPrice" : 57100,
    "openPrice" : 57100,
    "tradeDate" : "2025-07-02",
    "closePrice" : 56300
  }, {
    "volume" : 12792,
    "marketCap" : 675600000000,
    "lowPrice" : 56000,
    "highPrice" : 57000,
    "openPrice" : 56800,
    "tradeDate" : "2025-07-03",
    "closePrice" : 56300
  }, {
    "volume" : 25208,
    "marketCap" : 670800000000,
    "lowPrice" : 54800,
    "highPrice" : 56700,
    "openPrice" : 56300,
    "tradeDate" : "2025-07-04",
    "closePrice" : 55900
  }, {
    "volume" : 18049,
    "marketCap" : 668400000000,
    "lowPrice" : 55100,
    "highPrice" : 56400,
    "openPrice" : 55800,
    "tradeDate" : "2025-07-07",
    "closePrice" : 55700
  }, {
    "volume" : 21236,
    "marketCap" : 680400000000,
    "lowPrice" : 55700,
    "highPrice" : 56800,
    "openPrice" : 55700,
    "tradeDate" : "2025-07-08",
    "closePrice" : 56700
  }, {
    "volume" : 32717,
    "marketCap" : 696000000000,
    "lowPrice" : 56100,
    "highPrice" : 58200,
    "openPrice" : 56100,
    "tradeDate" : "2025-07-09",
    "closePrice" : 58000
  }, {
    "volume" : 21762,
    "marketCap" : 693600000000,
    "lowPrice" : 57100,
    "highPrice" : 58300,
    "openPrice" : 58000,
    "tradeDate" : "2025-07-10",
    "closePrice" : 57800
  }, {
    "volume" : 13277,
    "marketCap" : 692400000000,
    "lowPrice" : 57300,
    "highPrice" : 58000,
    "openPrice" : 57900,
    "tradeDate" : "2025-07-11",
    "closePrice" : 57700
  }, {
    "volume" : 65343,
    "marketCap" : 722400000000,
    "lowPrice" : 57300,
    "highPrice" : 60300,
    "openPrice" : 58000,
    "tradeDate" : "2025-07-14",
    "closePrice" : 60200
  }, {
    "volume" : 19627,
    "marketCap" : 714000000000,
    "lowPrice" : 59000,
    "highPrice" : 60300,
    "openPrice" : 60300,
    "tradeDate" : "2025-07-15",
    "closePrice" : 59500
  }, {
    "volume" : 16012,
    "marketCap" : 711600000000,
    "lowPrice" : 58600,
    "highPrice" : 59900,
    "openPrice" : 59400,
    "tradeDate" : "2025-07-16",
    "closePrice" : 59300
  }, {
    "volume" : 17266,
    "marketCap" : 712800000000,
    "lowPrice" : 58200,
    "highPrice" : 59700,
    "openPrice" : 59300,
    "tradeDate" : "2025-07-17",
    "closePrice" : 59400
  }, {
    "volume" : 11052,
    "marketCap" : 704400000000,
    "lowPrice" : 58200,
    "highPrice" : 59600,
    "openPrice" : 59500,
    "tradeDate" : "2025-07-18",
    "closePrice" : 58700
  }, {
    "volume" : 6049,
    "marketCap" : 698400000000,
    "lowPrice" : 58100,
    "highPrice" : 59100,
    "openPrice" : 58800,
    "tradeDate" : "2025-07-21",
    "closePrice" : 58200
  }, {
    "volume" : 10332,
    "marketCap" : 690000000000,
    "lowPrice" : 57400,
    "highPrice" : 58400,
    "openPrice" : 58200,
    "tradeDate" : "2025-07-22",
    "closePrice" : 57500
  }, {
    "volume" : 9946,
    "marketCap" : 688800000000,
    "lowPrice" : 56700,
    "highPrice" : 57900,
    "openPrice" : 57600,
    "tradeDate" : "2025-07-23",
    "closePrice" : 57400
  }, {
    "volume" : 12719,
    "marketCap" : 681600000000,
    "lowPrice" : 56200,
    "highPrice" : 58000,
    "openPrice" : 57900,
    "tradeDate" : "2025-07-24",
    "closePrice" : 56800
  }, {
    "volume" : 14645,
    "marketCap" : 687600000000,
    "lowPrice" : 56200,
    "highPrice" : 57800,
    "openPrice" : 56800,
    "tradeDate" : "2025-07-25",
    "closePrice" : 57300
  }, {
    "volume" : 20953,
    "marketCap" : 669600000000,
    "lowPrice" : 55800,
    "highPrice" : 57400,
    "openPrice" : 57300,
    "tradeDate" : "2025-07-28",
    "closePrice" : 55800
  }, {
    "volume" : 14566,
    "marketCap" : 686400000000,
    "lowPrice" : 55200,
    "highPrice" : 57200,
    "openPrice" : 55800,
    "tradeDate" : "2025-07-29",
    "closePrice" : 57200
  }, {
    "volume" : 9230,
    "marketCap" : 684000000000,
    "lowPrice" : 56700,
    "highPrice" : 57600,
    "openPrice" : 57200,
    "tradeDate" : "2025-07-30",
    "closePrice" : 57000
  }, {
    "volume" : 13555,
    "marketCap" : 687600000000,
    "lowPrice" : 56500,
    "highPrice" : 57900,
    "openPrice" : 57200,
    "tradeDate" : "2025-07-31",
    "closePrice" : 57300
  }, {
    "volume" : 19168,
    "marketCap" : 656400000000,
    "lowPrice" : 54600,
    "highPrice" : 57200,
    "openPrice" : 57200,
    "tradeDate" : "2025-08-01",
    "closePrice" : 54700
  }, {
    "volume" : 6878,
    "marketCap" : 658800000000,
    "lowPrice" : 54300,
    "highPrice" : 55700,
    "openPrice" : 54600,
    "tradeDate" : "2025-08-04",
    "closePrice" : 54900
  }, {
    "volume" : 7213,
    "marketCap" : 660000000000,
    "lowPrice" : 54900,
    "highPrice" : 56000,
    "openPrice" : 55000,
    "tradeDate" : "2025-08-05",
    "closePrice" : 55000
  }, {
    "volume" : 8848,
    "marketCap" : 672000000000,
    "lowPrice" : 55000,
    "highPrice" : 56700,
    "openPrice" : 55000,
    "tradeDate" : "2025-08-06",
    "closePrice" : 56000
  }, {
    "volume" : 21737,
    "marketCap" : 654000000000,
    "lowPrice" : 53900,
    "highPrice" : 56700,
    "openPrice" : 56700,
    "tradeDate" : "2025-08-07",
    "closePrice" : 54500
  }, {
    "volume" : 9078,
    "marketCap" : 654000000000,
    "lowPrice" : 54100,
    "highPrice" : 55000,
    "openPrice" : 54500,
    "tradeDate" : "2025-08-08",
    "closePrice" : 54500
  }, {
    "volume" : 8131,
    "marketCap" : 646800000000,
    "lowPrice" : 53500,
    "highPrice" : 54500,
    "openPrice" : 54400,
    "tradeDate" : "2025-08-11",
    "closePrice" : 53900
  }, {
    "volume" : 12703,
    "marketCap" : 651600000000,
    "lowPrice" : 53400,
    "highPrice" : 54400,
    "openPrice" : 53700,
    "tradeDate" : "2025-08-12",
    "closePrice" : 54300
  }, {
    "volume" : 12317,
    "marketCap" : 639600000000,
    "lowPrice" : 53200,
    "highPrice" : 54300,
    "openPrice" : 54300,
    "tradeDate" : "2025-08-13",
    "closePrice" : 53300
  }, {
    "volume" : 8816,
    "marketCap" : 637200000000,
    "lowPrice" : 52800,
    "highPrice" : 54000,
    "openPrice" : 53300,
    "tradeDate" : "2025-08-14",
    "closePrice" : 53100
  }, {
    "volume" : 6070,
    "marketCap" : 638400000000,
    "lowPrice" : 52800,
    "highPrice" : 53500,
    "openPrice" : 53300,
    "tradeDate" : "2025-08-18",
    "closePrice" : 53200
  }, {
    "volume" : 6634,
    "marketCap" : 636000000000,
    "lowPrice" : 52700,
    "highPrice" : 53700,
    "openPrice" : 53200,
    "tradeDate" : "2025-08-19",
    "closePrice" : 53000
  }, {
    "volume" : 9439,
    "marketCap" : 627600000000,
    "lowPrice" : 52000,
    "highPrice" : 53000,
    "openPrice" : 53000,
    "tradeDate" : "2025-08-20",
    "closePrice" : 52300
  }, {
    "volume" : 7851,
    "marketCap" : 637200000000,
    "lowPrice" : 52100,
    "highPrice" : 53700,
    "openPrice" : 52700,
    "tradeDate" : "2025-08-21",
    "closePrice" : 53100
  }, {
    "volume" : 6919,
    "marketCap" : 639600000000,
    "lowPrice" : 52700,
    "highPrice" : 54000,
    "openPrice" : 53100,
    "tradeDate" : "2025-08-22",
    "closePrice" : 53300
  }, {
    "volume" : 11199,
    "marketCap" : 637200000000,
    "lowPrice" : 52700,
    "highPrice" : 54300,
    "openPrice" : 53900,
    "tradeDate" : "2025-08-25",
    "closePrice" : 53100
  }, {
    "volume" : 5860,
    "marketCap" : 648000000000,
    "lowPrice" : 53100,
    "highPrice" : 54100,
    "openPrice" : 53300,
    "tradeDate" : "2025-08-26",
    "closePrice" : 54000
  }, {
    "volume" : 6981,
    "marketCap" : 646800000000,
    "lowPrice" : 53300,
    "highPrice" : 54200,
    "openPrice" : 53600,
    "tradeDate" : "2025-08-27",
    "closePrice" : 53900
  }, {
    "volume" : 10807,
    "marketCap" : 651600000000,
    "lowPrice" : 53600,
    "highPrice" : 55400,
    "openPrice" : 54300,
    "tradeDate" : "2025-08-28",
    "closePrice" : 54300
  }, {
    "volume" : 12404,
    "marketCap" : 667200000000,
    "lowPrice" : 54200,
    "highPrice" : 56000,
    "openPrice" : 54200,
    "tradeDate" : "2025-08-29",
    "closePrice" : 55600
  }, {
    "volume" : 13715,
    "marketCap" : 672000000000,
    "lowPrice" : 54800,
    "highPrice" : 56700,
    "openPrice" : 55600,
    "tradeDate" : "2025-09-01",
    "closePrice" : 56000
  }, {
    "volume" : 15052,
    "marketCap" : 655200000000,
    "lowPrice" : 54200,
    "highPrice" : 56400,
    "openPrice" : 55900,
    "tradeDate" : "2025-09-02",
    "closePrice" : 54600
  }, {
    "volume" : 5885,
    "marketCap" : 658800000000,
    "lowPrice" : 54500,
    "highPrice" : 55900,
    "openPrice" : 54600,
    "tradeDate" : "2025-09-03",
    "closePrice" : 54900
  }, {
    "volume" : 6190,
    "marketCap" : 667200000000,
    "lowPrice" : 55200,
    "highPrice" : 56300,
    "openPrice" : 55200,
    "tradeDate" : "2025-09-04",
    "closePrice" : 55600
  }, {
    "volume" : 3695,
    "marketCap" : 663600000000,
    "lowPrice" : 55300,
    "highPrice" : 56500,
    "openPrice" : 56400,
    "tradeDate" : "2025-09-05",
    "closePrice" : 55300
  }, {
    "volume" : 5610,
    "marketCap" : 668400000000,
    "lowPrice" : 55500,
    "highPrice" : 56400,
    "openPrice" : 55900,
    "tradeDate" : "2025-09-08",
    "closePrice" : 55700
  }, {
    "volume" : 8814,
    "marketCap" : 662400000000,
    "lowPrice" : 55100,
    "highPrice" : 56400,
    "openPrice" : 55600,
    "tradeDate" : "2025-09-09",
    "closePrice" : 55200
  }, {
    "volume" : 14246,
    "marketCap" : 666000000000,
    "lowPrice" : 54800,
    "highPrice" : 56000,
    "openPrice" : 55200,
    "tradeDate" : "2025-09-10",
    "closePrice" : 55500
  }, {
    "volume" : 8712,
    "marketCap" : 663600000000,
    "lowPrice" : 54600,
    "highPrice" : 56500,
    "openPrice" : 56500,
    "tradeDate" : "2025-09-11",
    "closePrice" : 55300
  }, {
    "volume" : 7016,
    "marketCap" : 662400000000,
    "lowPrice" : 54800,
    "highPrice" : 55900,
    "openPrice" : 55300,
    "tradeDate" : "2025-09-12",
    "closePrice" : 55200
  }, {
    "volume" : 11938,
    "marketCap" : 664800000000,
    "lowPrice" : 55200,
    "highPrice" : 56500,
    "openPrice" : 55200,
    "tradeDate" : "2025-09-15",
    "closePrice" : 55400
  }, {
    "volume" : 4321,
    "marketCap" : 670800000000,
    "lowPrice" : 55300,
    "highPrice" : 56000,
    "openPrice" : 55900,
    "tradeDate" : "2025-09-16",
    "closePrice" : 55900
  }, {
    "volume" : 5460,
    "marketCap" : 661200000000,
    "lowPrice" : 54900,
    "highPrice" : 55800,
    "openPrice" : 55800,
    "tradeDate" : "2025-09-17",
    "closePrice" : 55100
  }, {
    "volume" : 6348,
    "marketCap" : 660000000000,
    "lowPrice" : 55000,
    "highPrice" : 56000,
    "openPrice" : 55100,
    "tradeDate" : "2025-09-18",
    "closePrice" : 55000
  }, {
    "volume" : 17870,
    "marketCap" : 669600000000,
    "lowPrice" : 55100,
    "highPrice" : 56500,
    "openPrice" : 55400,
    "tradeDate" : "2025-09-19",
    "closePrice" : 55800
  }, {
    "volume" : 11307,
    "marketCap" : 663600000000,
    "lowPrice" : 54500,
    "highPrice" : 56400,
    "openPrice" : 56000,
    "tradeDate" : "2025-09-22",
    "closePrice" : 55300
  }, {
    "volume" : 10871,
    "marketCap" : 673200000000,
    "lowPrice" : 54600,
    "highPrice" : 56100,
    "openPrice" : 55600,
    "tradeDate" : "2025-09-23",
    "closePrice" : 56100
  }, {
    "volume" : 6646,
    "marketCap" : 662400000000,
    "lowPrice" : 54800,
    "highPrice" : 56100,
    "openPrice" : 56000,
    "tradeDate" : "2025-09-24",
    "closePrice" : 55200
  }, {
    "volume" : 4900,
    "marketCap" : 664800000000,
    "lowPrice" : 54800,
    "highPrice" : 55400,
    "openPrice" : 55300,
    "tradeDate" : "2025-09-25",
    "closePrice" : 55400
  }, {
    "volume" : 3281,
    "marketCap" : 663600000000,
    "lowPrice" : 54700,
    "highPrice" : 55400,
    "openPrice" : 55400,
    "tradeDate" : "2025-09-26",
    "closePrice" : 55300
  }, {
    "volume" : 9141,
    "marketCap" : 667200000000,
    "lowPrice" : 55000,
    "highPrice" : 56000,
    "openPrice" : 55300,
    "tradeDate" : "2025-09-29",
    "closePrice" : 55600
  }, {
    "volume" : 11495,
    "marketCap" : 656400000000,
    "lowPrice" : 54600,
    "highPrice" : 55900,
    "openPrice" : 55600,
    "tradeDate" : "2025-09-30",
    "closePrice" : 54700
  }, {
    "volume" : 20998,
    "marketCap" : 646800000000,
    "lowPrice" : 53600,
    "highPrice" : 55100,
    "openPrice" : 54800,
    "tradeDate" : "2025-10-01",
    "closePrice" : 53900
  }, {
    "volume" : 7857,
    "marketCap" : 644400000000,
    "lowPrice" : 53600,
    "highPrice" : 54500,
    "openPrice" : 53900,
    "tradeDate" : "2025-10-02",
    "closePrice" : 53700
  }, {
    "volume" : 9324,
    "marketCap" : 639600000000,
    "lowPrice" : 53200,
    "highPrice" : 54200,
    "openPrice" : 53800,
    "tradeDate" : "2025-10-10",
    "closePrice" : 53300
  }, {
    "volume" : 5162,
    "marketCap" : 639600000000,
    "lowPrice" : 52800,
    "highPrice" : 54000,
    "openPrice" : 53300,
    "tradeDate" : "2025-10-13",
    "closePrice" : 53300
  }, {
    "volume" : 5775,
    "marketCap" : 640800000000,
    "lowPrice" : 53200,
    "highPrice" : 54300,
    "openPrice" : 53700,
    "tradeDate" : "2025-10-14",
    "closePrice" : 53400
  }, {
    "volume" : 13318,
    "marketCap" : 642000000000,
    "lowPrice" : 53000,
    "highPrice" : 54000,
    "openPrice" : 53400,
    "tradeDate" : "2025-10-15",
    "closePrice" : 53500
  }, {
    "volume" : 6182,
    "marketCap" : 648000000000,
    "lowPrice" : 53500,
    "highPrice" : 54700,
    "openPrice" : 53500,
    "tradeDate" : "2025-10-16",
    "closePrice" : 54000
  }, {
    "volume" : 29982,
    "marketCap" : 636000000000,
    "lowPrice" : 52300,
    "highPrice" : 54200,
    "openPrice" : 53700,
    "tradeDate" : "2025-10-17",
    "closePrice" : 53000
  }, {
    "volume" : 16354,
    "marketCap" : 631200000000,
    "lowPrice" : 52200,
    "highPrice" : 53800,
    "openPrice" : 53800,
    "tradeDate" : "2025-10-20",
    "closePrice" : 52600
  }, {
    "volume" : 8362,
    "marketCap" : 633600000000,
    "lowPrice" : 52500,
    "highPrice" : 53400,
    "openPrice" : 52600,
    "tradeDate" : "2025-10-21",
    "closePrice" : 52800
  }, {
    "volume" : 3581,
    "marketCap" : 643200000000,
    "lowPrice" : 52600,
    "highPrice" : 53800,
    "openPrice" : 52700,
    "tradeDate" : "2025-10-22",
    "closePrice" : 53600
  }, {
    "volume" : 6723,
    "marketCap" : 648000000000,
    "lowPrice" : 53200,
    "highPrice" : 54200,
    "openPrice" : 53800,
    "tradeDate" : "2025-10-23",
    "closePrice" : 54000
  }, {
    "volume" : 6851,
    "marketCap" : 650400000000,
    "lowPrice" : 53500,
    "highPrice" : 54200,
    "openPrice" : 53700,
    "tradeDate" : "2025-10-24",
    "closePrice" : 54200
  }, {
    "volume" : 9866,
    "marketCap" : 645600000000,
    "lowPrice" : 53600,
    "highPrice" : 54500,
    "openPrice" : 54100,
    "tradeDate" : "2025-10-27",
    "closePrice" : 53800
  }, {
    "volume" : 30413,
    "marketCap" : 634800000000,
    "lowPrice" : 52300,
    "highPrice" : 54200,
    "openPrice" : 53800,
    "tradeDate" : "2025-10-28",
    "closePrice" : 52900
  }, {
    "volume" : 10356,
    "marketCap" : 632400000000,
    "lowPrice" : 52400,
    "highPrice" : 53300,
    "openPrice" : 52900,
    "tradeDate" : "2025-10-29",
    "closePrice" : 52700
  }, {
    "volume" : 16587,
    "marketCap" : 636000000000,
    "lowPrice" : 52400,
    "highPrice" : 53400,
    "openPrice" : 52600,
    "tradeDate" : "2025-10-30",
    "closePrice" : 53000
  }, {
    "volume" : 11615,
    "marketCap" : 631200000000,
    "lowPrice" : 52400,
    "highPrice" : 53100,
    "openPrice" : 52900,
    "tradeDate" : "2025-10-31",
    "closePrice" : 52600
  }, {
    "volume" : 20880,
    "marketCap" : 616800000000,
    "lowPrice" : 51300,
    "highPrice" : 52600,
    "openPrice" : 52500,
    "tradeDate" : "2025-11-03",
    "closePrice" : 51400
  }, {
    "volume" : 20736,
    "marketCap" : 619200000000,
    "lowPrice" : 51000,
    "highPrice" : 51600,
    "openPrice" : 51600,
    "tradeDate" : "2025-11-04",
    "closePrice" : 51600
  }, {
    "volume" : 27235,
    "marketCap" : 626400000000,
    "lowPrice" : 50000,
    "highPrice" : 55000,
    "openPrice" : 51500,
    "tradeDate" : "2025-11-05",
    "closePrice" : 52200
  }, {
    "volume" : 13057,
    "marketCap" : 634800000000,
    "lowPrice" : 51600,
    "highPrice" : 54100,
    "openPrice" : 52400,
    "tradeDate" : "2025-11-06",
    "closePrice" : 52900
  }, {
    "volume" : 11304,
    "marketCap" : 638400000000,
    "lowPrice" : 52300,
    "highPrice" : 54200,
    "openPrice" : 52900,
    "tradeDate" : "2025-11-07",
    "closePrice" : 53200
  }, {
    "volume" : 21753,
    "marketCap" : 661200000000,
    "lowPrice" : 53200,
    "highPrice" : 55300,
    "openPrice" : 53200,
    "tradeDate" : "2025-11-10",
    "closePrice" : 55100
  }, {
    "volume" : 22359,
    "marketCap" : 664800000000,
    "lowPrice" : 54400,
    "highPrice" : 55800,
    "openPrice" : 55800,
    "tradeDate" : "2025-11-11",
    "closePrice" : 55400
  }, {
    "volume" : 18346,
    "marketCap" : 678000000000,
    "lowPrice" : 55300,
    "highPrice" : 56600,
    "openPrice" : 55500,
    "tradeDate" : "2025-11-12",
    "closePrice" : 56500
  }, {
    "volume" : 14277,
    "marketCap" : 676800000000,
    "lowPrice" : 55900,
    "highPrice" : 57000,
    "openPrice" : 56800,
    "tradeDate" : "2025-11-13",
    "closePrice" : 56400
  }, {
    "volume" : 23299,
    "marketCap" : 680400000000,
    "lowPrice" : 55700,
    "highPrice" : 57200,
    "openPrice" : 56100,
    "tradeDate" : "2025-11-14",
    "closePrice" : 56700
  }, {
    "volume" : 10408,
    "marketCap" : 668400000000,
    "lowPrice" : 55500,
    "highPrice" : 57200,
    "openPrice" : 57200,
    "tradeDate" : "2025-11-17",
    "closePrice" : 55700
  }, {
    "volume" : 13749,
    "marketCap" : 652800000000,
    "lowPrice" : 54200,
    "highPrice" : 56100,
    "openPrice" : 56000,
    "tradeDate" : "2025-11-18",
    "closePrice" : 54400
  }, {
    "volume" : 4731,
    "marketCap" : 650400000000,
    "lowPrice" : 53900,
    "highPrice" : 55300,
    "openPrice" : 54500,
    "tradeDate" : "2025-11-19",
    "closePrice" : 54200
  }, {
    "volume" : 6259,
    "marketCap" : 674400000000,
    "lowPrice" : 54200,
    "highPrice" : 56300,
    "openPrice" : 54200,
    "tradeDate" : "2025-11-20",
    "closePrice" : 56200
  }, {
    "volume" : 8604,
    "marketCap" : 669600000000,
    "lowPrice" : 55200,
    "highPrice" : 56700,
    "openPrice" : 56000,
    "tradeDate" : "2025-11-21",
    "closePrice" : 55800
  }, {
    "volume" : 3633,
    "marketCap" : 664800000000,
    "lowPrice" : 55350,
    "highPrice" : 56500,
    "openPrice" : 56500,
    "tradeDate" : "2025-11-24",
    "closePrice" : 55400
  }, {
    "volume" : 7000,
    "marketCap" : 655200000000,
    "lowPrice" : 54400,
    "highPrice" : 56000,
    "openPrice" : 56000,
    "tradeDate" : "2025-11-25",
    "closePrice" : 54600
  }, {
    "volume" : 6271,
    "marketCap" : 654000000000,
    "lowPrice" : 54200,
    "highPrice" : 55100,
    "openPrice" : 54700,
    "tradeDate" : "2025-11-26",
    "closePrice" : 54500
  }, {
    "volume" : 2820,
    "marketCap" : 660000000000,
    "lowPrice" : 54200,
    "highPrice" : 55100,
    "openPrice" : 54600,
    "tradeDate" : "2025-11-27",
    "closePrice" : 55000
  }, {
    "volume" : 7073,
    "marketCap" : 657600000000,
    "lowPrice" : 54400,
    "highPrice" : 55500,
    "openPrice" : 54900,
    "tradeDate" : "2025-11-28",
    "closePrice" : 54800
  }, {
    "volume" : 4548,
    "marketCap" : 664800000000,
    "lowPrice" : 54500,
    "highPrice" : 55500,
    "openPrice" : 55100,
    "tradeDate" : "2025-12-01",
    "closePrice" : 55400
  }, {
    "volume" : 7293,
    "marketCap" : 662400000000,
    "lowPrice" : 55000,
    "highPrice" : 55800,
    "openPrice" : 55600,
    "tradeDate" : "2025-12-02",
    "closePrice" : 55200
  }, {
    "volume" : 7551,
    "marketCap" : 664800000000,
    "lowPrice" : 55100,
    "highPrice" : 56400,
    "openPrice" : 55900,
    "tradeDate" : "2025-12-03",
    "closePrice" : 55400
  }, {
    "volume" : 6706,
    "marketCap" : 663600000000,
    "lowPrice" : 55000,
    "highPrice" : 56200,
    "openPrice" : 55800,
    "tradeDate" : "2025-12-04",
    "closePrice" : 55300
  }, {
    "volume" : 3943,
    "marketCap" : 660000000000,
    "lowPrice" : 54900,
    "highPrice" : 55900,
    "openPrice" : 55900,
    "tradeDate" : "2025-12-05",
    "closePrice" : 55000
  }, {
    "volume" : 9447,
    "marketCap" : 660000000000,
    "lowPrice" : 54600,
    "highPrice" : 56000,
    "openPrice" : 55000,
    "tradeDate" : "2025-12-08",
    "closePrice" : 55000
  }, {
    "volume" : 3023,
    "marketCap" : 656400000000,
    "lowPrice" : 54400,
    "highPrice" : 55000,
    "openPrice" : 54800,
    "tradeDate" : "2025-12-09",
    "closePrice" : 54700
  }, {
    "volume" : 6351,
    "marketCap" : 650400000000,
    "lowPrice" : 54100,
    "highPrice" : 54800,
    "openPrice" : 54400,
    "tradeDate" : "2025-12-10",
    "closePrice" : 54200
  }, {
    "volume" : 4971,
    "marketCap" : 661200000000,
    "lowPrice" : 54200,
    "highPrice" : 55700,
    "openPrice" : 54500,
    "tradeDate" : "2025-12-11",
    "closePrice" : 55100
  }, {
    "volume" : 3156,
    "marketCap" : 669600000000,
    "lowPrice" : 55100,
    "highPrice" : 56100,
    "openPrice" : 55100,
    "tradeDate" : "2025-12-12",
    "closePrice" : 55800
  }, {
    "volume" : 6465,
    "marketCap" : 672000000000,
    "lowPrice" : 55300,
    "highPrice" : 56400,
    "openPrice" : 55800,
    "tradeDate" : "2025-12-15",
    "closePrice" : 56000
  }, {
    "volume" : 9136,
    "marketCap" : 669600000000,
    "lowPrice" : 54900,
    "highPrice" : 56300,
    "openPrice" : 56200,
    "tradeDate" : "2025-12-16",
    "closePrice" : 55800
  }, {
    "volume" : 4823,
    "marketCap" : 678000000000,
    "lowPrice" : 55600,
    "highPrice" : 56500,
    "openPrice" : 55700,
    "tradeDate" : "2025-12-17",
    "closePrice" : 56500
  }, {
    "volume" : 3122,
    "marketCap" : 666000000000,
    "lowPrice" : 55500,
    "highPrice" : 56500,
    "openPrice" : 56400,
    "tradeDate" : "2025-12-18",
    "closePrice" : 55500
  }, {
    "volume" : 12613,
    "marketCap" : 663600000000,
    "lowPrice" : 55200,
    "highPrice" : 56200,
    "openPrice" : 56200,
    "tradeDate" : "2025-12-19",
    "closePrice" : 55300
  }, {
    "volume" : 6553,
    "marketCap" : 668400000000,
    "lowPrice" : 55200,
    "highPrice" : 56400,
    "openPrice" : 56400,
    "tradeDate" : "2025-12-22",
    "closePrice" : 55700
  }, {
    "volume" : 2974,
    "marketCap" : 667200000000,
    "lowPrice" : 55600,
    "highPrice" : 56200,
    "openPrice" : 55800,
    "tradeDate" : "2025-12-23",
    "closePrice" : 55600
  } ],
  "stockCode" : "057050"
}